Workbook

Sheet Division 01
A1: Group | B1: Class | C1: Sub- Class | D1: Item | E1: Sub-Item | F1: Description | G1: 2018 UN COICOP | H1: 2009 PCOICOP | I1: CPC 2.1
F3: Division 01. FOOD AND NON-ALCOHOLIC BEVERAGES
F5: Division 01 covers food (01.1) and non-alcoholic beverages (01.2) purchased by the household mainly for consumption or preparation at home. It excludes food and non-alcoholic beverages that are provided as part of a food serving service (Division 11).
F7: Services for processing primary goods to produce food and non-alcoholic beverages for own consumption are also included in this Division (01.3).
F9: Food is composed of all edible goods that are purchased and consumed by the household with the purpose of nourishing. It includes: cereals and cereal products; meat; fish and other seafood; milk, other dairy products and eggs; oils and fats; fruit and nuts; vegetables, tubers, plantains, cooking bananas and pulses; sugar, confectionery and desserts; salt, sauces and condiments, spices and culinary herbs and seeds.
F11: Division 01 also includes baby food and ready-made food that can be eaten as it is or after heating. Non-alcoholic beverages include drinks that do not contain any alcohol.
A13: 01.1 | F13: FOOD
F15: Food purchased by the household mainly for consumption or preparation at home. It excludes food that is provided as part of a food serving service.
F17: Food is composed of all edible goods that are purchased and consumed by the household with the purpose of nourishing. It includes: cereals and cereal products; meat; fish and other seafood; milk, other dairy products and eggs; oils and fats; fruit and nuts; vegetables, tubers, plantains, cooking bananas and pulses; sugar, confectionery and desserts; salt, sauces and condiments, spices and culinary herbs and seeds.
F19: This group includes:
F21: - products that need to be cooked and further prepared as well as ready-made food.
F23: This group excludes:
F25: - local delivery services of food or drinks, when separately invoiced (07.4.9.2);
F26: - products for animal feeding (09.3.2.2);
F27: - food provided by food serving services (Division 11).
B30: 01.1.1 | F30: Cereals and cereal products (ND)
C32: 01.1.1.1 | F32: Cereals (ND)
F34: Dried grains of cereals, whether or not broken or precooked (steamed), but not further prepared.
F36: This subclass includes:
F38: - wheat;
F40: - rice, including parboiled rice;
F42: - sorghum;
F44: - barley;
F46: - millet;
F48: - maize (corn);
F50: - quinoa;
F52: - teff;
F54: Includes also:
F56: - bulgur;
... F86: - seeds for planting (09.3.1.2).
D88: 01.1.1.11 | E88: 01.1.1.110 | F88: Wheat | G88: 01.1.1.11 | H88: 01.1.131p | I88: 01112
D89: 01.1.1.12 | F89: Rice
E90: 01.1.1.121 | F90: Rice, except NFA rice, well milled | G90: 01.1.1.12 | H90: 01.1.111 | I90: 23161p
E91: 01.1.1.122 | F91: Rice, except NFA rice, regular milled | G91: 01.1.1.12 | H91: 01.1.113 | I91: 23161p
E92: 01.1.1.123 | F92: Rice, except NFA rice, special | G92: 01.1.1.12 | H92: 01.1.112p 01.1.119p | I92: 23161p
E93: 01.1.1.124 | F93: Rice, except NFA rice, over milled, broken rice | G93: 01.1.1.12 | H93: 01.1.115 | I93: 23161p
E94: 01.1.1.125 | F94: NFA Rice | G94: 01.1.1.12 | H94: 01.1.114 | I94: 23161p
E95: 01.1.1.126 | F95: Rice, under milled, brown | G95: 01.1.1.12 | H95: 01.1.112p | I95: 23162p
E96: 01.1.1.127 | F96: Rice, under milled, red | G96: 01.1.1.12 | H96: 01.1.119p | I96: 23162p
E97: 01.1.1.128 | F97: Rice, milled, glutinous | G97: 01.1.1.12 | H97: 01.1.119p | I97: 23161p
E98: 01.1.1.129 | F98: Other rice, n.e.c. | G98: 01.1.1.12 | H98: 01.1.119p | I98: 23161p 23162p
D99: 01.1.1.13 | E99: 01.1.1.130 | F99: Sorghum | G99: 01.1.1.13 | H99: 01.1.139p | I99: 01142
D100: 01.1.1.14 | E100: 01.1.1.140 | F100: Barley | G100: 01.1.1.14 | H100: 01.1.132p | I100: 01152
D101: 01.1.1.15 | F101: Millet
E102: 01.1.1.151 | F102: Millet, glutinous | G102: 01.1.1.15 | H102: 01.1.139p | I102: 01182
E103: 01.1.1.159 | F103: Other millet, n.e.c. | G103: 01.1.1.15 | H103: 01.1.139p | I103: 01182
D104: 01.1.1.16 | F104: Corn
E105: 01.1.1.161 | F105: Corn, on the cob, yellow | G105: 01.1.1.16 | H105: 01.1.121 | I105: 01122p
E106: 01.1.1.162 | F106: Corn, on the cob, white | G106: 01.1.1.16 | H106: 01.1.122 | I106: 01122p
E107: 01.1.1.163 | F107: Whole corn, grain | G107: 01.1.1.16 | H107: 01.1.123 | I107: 01122p
E108: 01.1.1.164 | F108: Glutinous corn | G108: 01.1.1.16 | H108: 01.1.124 | I108: 01122p
E109: 01.1.1.165 | F109: Popcorn (variety) | G109: 01.1.1.16 | H109: 01.1.125 | I109: 01122p
E110: 01.1.1.166 | F110: Corn grits, milled | G110: 01.1.1.16 | H110: 01.1.126 | I110: 01122p
E111: 01.1.1.169 | F111: Other corn (milled or unmilled), n.e.c. | G111: 01.1.1.16 | H111: 01.1.129p | I111: 01122p
D112: 01.1.1.17 | E112: 01.1.1.170 | F112: Quinoa | G112: 01.1.1.17 | H112: 01.1.139p | I112: 01194
D113: 01.1.1.18 | E113: 01.1.1.180 | F113: Teff | G113: 01.1.1.18 | H113: 01.1.139p | I113: 01199p
D114: 01.1.1.19 | F114: Other cereals
E115: 01.1.1.191 | F115: Oats | G115: 01.1.1.19 | H115: 01.1.133 | I115: 01172
E116: 01.1.1.192 | F116: Rye | G116: 01.1.1.19 | H116: 01.1.134 | I116: 01162
E117: 01.1.1.193 | F117: Job's tears grain (Adlay butil) | G117: 01.1.1.19 | H117: 01.1.139p | I117: 01199p
E118: 01.1.1.199 | F118: Other | G118: 01.1.1.19 | H118: 01.1.139p | I118: 01199p
C120: 01.1.1.2 | F120: Flour of cereals (ND) | H120: =D120
F122: Flour of cereals mentioned in Subclass 01.1.1.1 whether instant (precooked – steamed – or added with yeasts) or not.
F124: This sub-class includes:
F125: - flour of cereals mentioned in Subclass 01.1.1.1.
F127: Includes also:
F128: - instant flour for bakery products added with yeasts;
F129: - polenta flour, whether instant (pre-steamed) or not.
F131: This sub-class excludes:
F132: - flour as baby food, baby rice cereals and other baby cereals (01.1.9.2).
D134: 01.1.1.21 | F134: Flour of wheat
E135: 01.1.1.211 | F135: All-purpose flour | G135: 01.1.1.21 | H135: 01.1.131p | I135: 23110p
E136: 01.1.1.212 | F136: Cake flour | G136: 01.1.1.21 | H136: 01.1.131p | I136: 23110p
E137: 01.1.1.219 | F137: Other flour of wheat, n.e.c. | G137: 01.1.1.21 | H137: 01.1.131p | I137: 23110p
D138: 01.1.1.22 | E138: 01.1.1.220 | F138: Flour of rice | G138: 01.1.1.22 | H138: 01.1.137 | I138: 23120p
D139: 01.1.1.23 | E139: 01.1.1.230 | F139: Flour of sorghum | G139: 01.1.1.23 | H139: 01.1.139p | I139: 23120p
D140: 01.1.1.24 | E140: 01.1.1.240 | F140: Flour of barley | G140: 01.1.1.24 | H140: 01.1.132p | I140: 23120p
D141: 01.1.1.25 | E141: 01.1.1.250 | F141: Flour of millet | G141: 01.1.1.25 | H141: 01.1.139p | I141: 23120p
D142: 01.1.1.26 | F142: Flour of maize (corn) or cornmeal
E143: 01.1.1.261 | F143: Corn starch | G143: 01.1.1.26 | H143: 01.1.129p | I143: 23220p
E144: 01.1.1.269 | F144: Other flour of maize (corn) or cornmeal, n.e.c | G144: 01.1.1.26 | H144: 01.1.136 01.1.129p | I144: 23120p
D145: 01.1.1.27 | E145: 01.1.1.270 | F145: Flour of quinoa | G145: 01.1.1.27 | H145: 01.1.139p | I145: 23120p
D146: 01.1.1.28 | E146: 01.1.1.280 | F146: Flour of teff | G146: 01.1.1.28 | H146: 01.1.139p | I146: 23120p
D147: 01.1.1.29 | E147: 01.1.1.290 | F147: Other flours of cereals | G147: 01.1.1.29 | H147: 01.1.139p | I147: 23120p
C149: 01.1.1.3 | F149: Bread and bakery products (ND)
F151: This sub-class includes:
F153: - bread and bread rolls;
F155: - crisp bread, rusks, toasted bread, crackers;
F157: - tortillas;
F159: - injera;
F161: - pizza bases without topping, whether pre-cooked or not;
F163: - gingerbread and the like;
F165: - sweet biscuits (cookies);
F167: - waffles and wafers;
F169: - ice cream cones;
F171: - crumpets, muffins, croissants, cakes, sweet tarts, sweet pies, and other pastry goods and cakes.
F173: This sub-class excludes:
F175: - pizza (with topping), quiche, meat or fish pies (01.1.9.1).
D177: 01.1.1.31 | F177: Bread
E178: 01.1.1.311 | F178: Loaf bread | G178: 01.1.1.31 | H178: 01.1.151 | I178: 23490p
...

Sheet Division 02
A1: Group | B1: Class | C1: Sub- Class | D1: Item | E1: Sub-Item | F1: Description | G1: 2018 UN COICOP | H1: 2009 PCOICOP | I1: CPC 2.1
F3: DIVISION 02. ALCOHOLIC BEVERAGES, TOBACCO AND NARCOTICS | G3: =D3
F5: Division 02 covers the purchase of alcoholic beverages (02.1) and of tobacco products (02.3) and narcotics (02.4), regardless of where these are consumed but not provided as part of a food and beverage serving service.
F7: Also includes low and non-alcoholic beverages, which are generally alcoholic, such as non-alcoholic beer. Services for the production of alcohol for own consumption (02.2) are also included in this Division.
F9: It excludes alcoholic beverages purchased for immediate consumption in hotels restaurants, cafés, bars, kiosks, street vendors, automatic vending machines, etc. (11.1.1).
A11: 02.1 | F11: ALCOHOLIC BEVERAGES | G11: =C11
F13: The beverages classified here include low or non-alcoholic beverages which generally contain some alcohol.
B15: 02.1.1 | C15: 02.1.1.0 | D15: 02.1.1.00 | F15: Spirits and liquors (ND)
E17: 02.1.1.001 | F17: Whisky | G17: =C15 -> 02.1.1.0 | H17: 02.1.110 | I17: 24131
E18: 02.1.1.002 | F18: Rum | G18: 02.1.1.0 | H18: 02.1.120 | I18: 24131
E19: 02.1.1.003 | F19: Gin | G19: 02.1.1.0 | H19: 02.1.130 | I19: 24131
E20: 02.1.1.004 | F20: Brandy | G20: 02.1.1.0 | H20: 02.1.140 | I20: 24131
E21: 02.1.1.005 | F21: Vodka (lambanog, etc.) | G21: 02.1.1.0 | H21: 02.1.150 | I21: 24131
E22: 02.1.1.006 | F22: Tequila | G22: 02.1.1.0 | H22: 02.1.190 p | I22: 24131
E23: 02.1.1.009 | F23: Other spirits and liquors, n.e.c. | G23: 02.1.1.0 | H23: 02.1.190 p | I23: 24139
B25: 02.1.2 | F25: Wine (ND) | G25: =C25
C27: 02.1.2.1 | D27: 02.1.2.10 | F27: Wine from grapes (ND)
E28: 02.1.2.101 | F28: Champagne and sparkling wines | G28: =C27 -> 02.1.2.1 | H28: 02.1.270 | I28: 24211
E29: 02.1.2.102 | F29: Wine from grapes other than champagne and sparkling wine | G29: 02.1.2.1 | H29: 02.1.290 p | I29: 24212
C31: 02.1.2.2 | D31: 02.1.2.20 | F31: Wine from other sources (ND)
E32: 02.1.2.201 | F32: Tuba (palm) wine | G32: =C31 -> 02.1.2.2 | H32: 02.1.210 | I32: 24220
E33: 02.1.2.202 | F33: Basi wine | G33: 02.1.2.2 | H33: 02.1.220 | I33: 24220
E34: 02.1.2.203 | F34: Mango wine | G34: 02.1.2.2 | H34: 02.1.230 | I34: 24220
E35: 02.1.2.204 | F35: Wine based aperitifs (ube wine, rice wine (sake), kasuy (cashew) wine, etc.) | G35: 02.1.2.2 | H35: 02.1.240 | I35: 24220
E36: 02.1.2.205 | F36: Cider and perry | G36: 02.1.2.2 | H36: 02.1.250 | I36: 24230
E37: 02.1.2.206 | F37: Fortified wines | G37: 02.1.2.2 | H37: 02.1.260 | I37: 24220
E38: 02.1.2.207 | F38: Lambanog wine | G38: 02.1.2.2 | H38: 02.1.290p | I38: 24220
E39: 02.1.2.208 | F39: Calamansi wine | G39: 02.1.2.2 | H39: 02.1.290p | I39: 24220
E40: 02.1.2.209 | F40: Other wine from other sources (e.g. medicinal wine (sioktong), duhat (plum) wine , bignay/bugnay (wild berry wine), strawberry wine, raisin wine, duhat wine, etc.) | G40: 02.1.2.2 | H40: 02.1.290p | I40: 24220
B42: 02.1.3 | C42: 02.1.3.0 | D42: 02.1.3.00 | F42: Beer (ND)
E44: 02.1.3.001 | F44: Beer made from malt | G44: =C42 -> 02.1.3.0 | H44: 02.1.310 | I44: 24310
E45: 02.1.3.002 | F45: Ale | G45: 02.1.3.0 | H45: 02.1.320 | I45: 24320
E46: 02.1.3.003 | F46: Lager | G46: 02.1.3.0 | H46: 02.1.330 | I46: 24320
E47: 02.1.3.004 | F47: Porter | G47: 02.1.3.0 | H47: 02.1.340 | I47: 24320
E48: 02.1.3.005 | F48: Low and non-alcoholic beer | G48: 02.1.3.0 | H48: 02.1.350 | I48: 24320
E49: 02.1.3.009 | F49: Other beer, n.e.c | G49: 02.1.3.0 | H49: 02.1.390 | I49: 24320
B51: 02.1.9 | C51: 02.1.9.0 | D51: 02.1.9.00 | F51: Other alcoholic beverages (ND)
E53: 02.1.9.001 | F53: Mixed alcohol-based drinks (gin pomelo, shandy, cola beer) | G53: =C51 -> 02.1.9.0 | H53: NEW | I53: 24139
E54: 02.1.9.009 | F54: Other alcoholic beverages, n.e.c. | G54: 02.1.9.0 | H54: NEW | I54: 24139
A56: 02.2 | B56: 02.2.0 | C56: 02.2.0.0 | D56: 02.2.0.00 | E56: 02.2.0.000 | F56: ALCOHOL PRODUCTION SERVICES
F58: Services purchased for the processing of primary products provided by households to produce alcohol for own final consumption by households.
F60: This subclass includes:
F61: - fruit/vegetable crushing and pressing services for the production of alcoholic beverages;
F62: - distilling and fermentation services;
F63: - brewing services;
F64: - aging and bottling services.
A66: 02.3 | F66: TOBACCO | G66: =C66
F68: This group covers all purchases of tobacco and tobacco products by households, including purchases of tobacco in restaurants, cafés, bars, service stations, etc. due to these venues not adding value, or a service, to the tobacco products sold. The consumption of tobacco through shisha or hookah pipes in these venues, such as restaurants, cafés or bars, are included in Division 11 as the venue does provide a service. Electronic cigarette refills are included in this group – even though they do not contain tobacco – as they are a substitute for smoking tobacco products.
B70: 02.3.0 | F70: Tobacco (ND) | G70: =C70
C71: 02.3.0.1 | D71: 02.3.0.10 | E71: 02.3.0.100 | F71: Cigarettes (ND) | G71: =C71 -> 02.3.0.1 | H71: 02.2.010 | I71: 25020
C72: 02.3.0.2 | D72: 02.3.0.20 | E72: 02.3.0.200 | F72: Cigars (ND) | G72: =C72 -> 02.3.0.2 | H72: 02.2.020 | I72: 25020
C73: 02.3.0.3 | D73: 02.3.0.30 | E73: 02.3.0.300 | F73: Dissolvable tobacco | G73: 02.3.0.9 | H73: 02.2.090 p | I73: 25090
C75: 02.3.0.9 | D75: 02.3.0.90 | F75: Other tobacco products (ND)
E76: 02.3.0.901 | F76: Pipe tobacco sniff/snuff tobacco | G76: =C75 -> 02.3.0.9 | H76: 02.2.030 | I76: 25090
E77: 02.3.0.902 | F77: Chewing tobacco | G77: 02.3.0.9 | H77: 02.2.040 | I77: 25090
E78: 02.3.0.903 | F78: Cigarette papers | G78: 02.3.0.9 | H78: 02.2.050 | I78: 25090
E79: 02.3.0.904 | F79: Tobacco leaves/Oral tobacco packets | G79: 02.3.0.9 | H79: 02.2.090 p | I79: 25010
E80: 02.3.0.905 | F80: Electronic cigarette refills | G80: 02.3.0.9 | H80: 02.2.090 p | I80: 25090
E81: 02.3.0.906 | F81: Electronically Heated Tobacco Products (EHTP) | G81: 02.3.0.9 | H81: 02.2.090 p | I81: 25090
E82: 02.3.0.909 | F82: Other tobacco products, n.e.c. | G82: 02.3.0.9p | H82: 02.2.090 p | I82: 25090
A84: 02.4 | F84: NARCOTICS | G84: =C84
F86: This group covers all narcotics purchased by households, both legal and illegal.
B88: 02.4.0 | C88: 02.4.0.0 | F88: Narcotics (ND)
D89: 02.4.0.01 | E89: 02.4.0.010 | F89: Marijuana, opium, cocaine and their derivatives | G89: 02.4.0.0 | H89: 02.3.010
D91: 02.4.0.02 | F91: Other vegetables based narcotics | G91: 02.4.0.0 | H91: 02.3.020
E92: 02.4.0.021 | F92: Betel leaves | G92: 02.4.0.0 | H92: 02.3.020 | I92: 03250 p
E93: 02.4.0.022 | F93: Betel nuts | G93: 02.4.0.0 | H93: 02.3.020 | I93: 01379 p
E94: 02.4.0.029 | F94: Other vegetables based narcotics | G94: 02.4.0.0 | H94: 02.3.020 | I94: 03250 p
D96: 02.4.0.09 | E96: 02.4.0.090 | F96: Other narcotics including chemicals, man-made drugs and synthetic drugs | G96: 02.4.0.0 | H96: 02.3.090 | I96: 03250 p

Sheet Completeness(1)
A1: 01.1.111
A2: 01.1.112
A3: 01.1.113
A4: 01.1.114
A5: 01.1.115
A6: 01.1.119
A7: 01.1.121
A8: 01.1.122
A9: 01.1.123
A10: 01.1.124
A11: 01.1.125
A12: 01.1.126
... A294: 01.2.249

Sheet Division 03
A1: Group | B1: Class | C1: Sub- Class | D1: Item | E1: Sub-Item | F1: Description | G1: 2018 UN COICOP | H1: 2009 PCOICOP | I1: CPC 2.1
F3: DIVISION 03. CLOTHING AND FOOTWEAR
F5: Division 03 covers all clothing materials, garments, articles and accessories (03.1), footwear (03.2), and related services including cleaning, repair and hire of clothing (03.1.4.) and footwear (03.2.2). The purchase of second-hand clothing and footwear should be included in the same classes as the new articles as the purpose is the same. Unisex garments and footwear should be classified according to the gender of the person wearing them.
F7: Excludes sport-and game-specific sports- and footwear (09.2.2.1).
A9: 03.1 | F9: CLOTHING | G9: =C9
F11: The clothing classified in this group covers materials purchased to be transformed into clothing, garments and accessories and services related to clothing.
F13: Made-to-measure refers to the service of providing custom fitted clothing when the retailer supplies all of the materials and is included in Group 03.1.2 (Garments) as the cost of the garment usually outweighs the cost of the service. Tailoring refers to creating clothing garments where the main material is supplied by the customer and is classified in Group 03.1.4 (Cleaning, repair, tailoring and hire of clothing) as the service is the higher expenditure.
B15: 03.1.1 | C15: 03.1.1.0 | D15: 03.1.1.00 | F15: Clothing materials (SD)
F17: This sub-class includes:
F19: - clothing materials of natural fibres, of synthetic fibres and of their mixtures;
F20: - leather, fur, fusible webbing, wadding and felt filling for making wearing apparel.
F22: This sub-class excludes:
F23: - furnishing fabrics (05.2.1.1).
E25: 03.1.1.001 | F25: Cotton and linens | G25: =C15 -> 03.1.1.0 | H25: 03.1.110 | I25: 26160 p
E26: 03.1.1.002 | F26: Clothing made from synthetic fibers | G26: 03.1.1.0 | H26: 03.1.120 | I26: 26710 p
E27: 03.1.1.009 | F27: Other clothing materials, n.e.c. | G27: 03.1.1.0 | H27: 03.1.190 | I27: 26510 p
B29: 03.1.2 | F29: Garments (SD) | G29: =C29
F31: Garments for men or boys, women or girls and infants, either ready-to-wear or made-to-measure, in all materials (including leather, furs, plastics and rubber), for everyday wear, for sport or for work.
F33: This class includes:
F35: - capes, overcoats, raincoats, anoraks, parkas, blousons, jackets, trousers, waistcoats, suits, costumes, dresses, skirts, etc.;
F37: - shirts, blouses, pullovers, sweaters, cardigans, shorts, swimsuits, tracksuits, jogging suits, sweatshirts, t-shirts, leotards, etc.;
F39: - vests, underpants, socks, stockings, tights, petticoats, brassières, knickers, slips, girdles, corsets, body stockings, etc.;
F41: - pajamas, nightshirts, nightdresses, housecoats, dressing gowns, bathrobes, etc.;
F43: - traditional garments.
F45: This class excludes:
F47: - tailoring services when the customer supplies the material (03.1.4.2);
F49: - articles of medical hosiery, such as elasticated stockings (06.1.2.2);
F51: - babies’ napkins, cloth diapers, cloth nappies (13.2.9.1).
C53: 03.1.2.1 | D53: 03.1.2.10 | F53: Garments for men or boys (SD)
F55: This subclass includes either ready-to-wear or made-to-measure, in all materials (including leather, furs, plastics and rubber), for everyday wear, for sport or for work.
E57: 03.1.2.101 | F57: Pants, shorts | G57: =C53 -> 03.1.2.1 | H57: 03.1.211 03.1.231 03.1.241 | I57: 28231
E58: 03.1.2.102 | F58: T-shirts, polo shirts, undershirts, camisatsino | G58: 03.1.2.1 | H58: 03.1.212 03.1.232 03.1.242 | I58: 28232
E59: 03.1.2.103 | F59: Underwear (supporter, brief, etc.) | G59: 03.1.2.1 | H59: 03.1.213 03.1.233 03.1.243 | I59: 28232
E60: 03.1.2.104 | F60: Socks, sports socks | G60: 03.1.2.1 | H60: 03.1.214 03.1.234 03.1.244 | I60: 28232
E61: 03.1.2.105 | F61: Suits, coats, jackets, raincoats, sweater, capes and trousers | G61: 03.1.2.1 | H61: 03.1.235 03.1.245 | I61: 28231
E62: 03.1.2.106 | F62: Track suits, swimwear, jogging suits, sweatshirts | G62: 03.1.2.1 | H62: 03.1.281 03.1.282 03.1.284 03.1.285 | I62: 28236
E63: 03.1.2.109 | F63: Other garments for men or boys, n.e.c. | G63: 03.1.2.1 | H63: 03.1.219 | I63: 28231 28232 28238
C65: 03.1.2.2 | D65: 03.1.2.20 | F65: Garments for women or girls (SD)
E67: 03.1.2.201 | F67: Dress, suits | G67: =C65 -> 03.1.2.2 | H67: 03.1.221 03.1.251 03.1.261 | I67: 28233
E68: 03.1.2.202 | F68: Pants, shorts, skirts | G68: 03.1.2.2 | H68: 03.1.222 03.1.252 03.1.262 | I68: 28233
E69: 03.1.2.203 | F69: Blouses, t-shirts, skirts | G69: 03.1.2.2 | H69: 03.1.223 03.1.253 03.1.263 | I69: 28233 28234
E70: 03.1.2.204 | F70: Underwear (panties, chemise, bra, half slip, girdles, etc.) | G70: 03.1.2.2 | H70: 03.1.224 03.1.254 03.1.264 | I70: 28237
E71: 03.1.2.205 | F71: Stockings, panty hose, socks, sports socks, tights | G71: 03.1.2.2 | H71: 03.1.225 03.1.255 03.1.265 | I71: 28237
E72: 03.1.2.206 | F72: Raincoats, jackets, sweater, capes | G72: 03.1.2.2 | H72: 03.1.226 03.1.256 03.1.266 | I72: 28231 28238
E73: 03.1.2.207 | F73: Track suits, swimwear, jogging suits, sweatshirts, leotards | G73: 03.1.2.2 | H73: 03.1.281 03.1.282 03.1.283 03.1.284 03.1.286 | I73: 28236
E74: 03.1.2.209 | F74: Other garments for women (Duster, pajamas, etc.) | G74: 03.1.2.2 | H74: 03.1.229 | I74: 28233 28234 28237 28238
C76: 03.1.2.3 | D76: 03.1.2.30 | F76: Garments for infants (0 to under 2 years) (SD)
E78: 03.1.2.301 | F78: Dress | G78: =C76 -> 03.1.2.3 | H78: 03.1.271 | I78: 28237
E79: 03.1.2.302 | F79: Briefs and panties | G79: 03.1.2.3 | H79: 03.1.272 | I79: 28237
E80: 03.1.2.303 | F80: Shirt, tie-side shirt, sweatshirt, sando | G80: 03.1.2.3 | H80: 03.1.273 | I80: 28237
E81: 03.1.2.304 | F81: Pants, shorts, skirts, pajamas | G81: 03.1.2.3 | H81: 03.1.274 | I81: 28237
E82: 03.1.2.309 | F82: Other garments for infants, n.e.c. | G82: 03.1.2.3 | H82: 03.1.279 | I82: 28237
C84: 03.1.2.4 | D84: 03.1.2.40 | E84: 03.1.2.400 | F84: School uniforms (SD) | G84: =C84 -> 03.1.2.4 | H84: 03.1.231 p 03.1.232 p 03.1.239 p 03.1.241 p 03.1.242 p 03.1.249 p 03.1.251 p 03.1.252 p 03.1.259 p 03.1.261 p 03.1.262 p 03.1.269 p 03.1.231 p 03.1.290 p 03.1.239 p | I84: 2823 p
B86: 03.1.3 | F86: Other articles of clothing and clothing accessories (SD) | G86: =C86
C88: 03.1.3.1 | D88: 03.1.3.10 | F88: Other articles of clothing (SD)
F90: This sub-class includes:
F92: - ties, handkerchiefs, scarves, gloves, mittens, muffs, belts, braces, aprons, smocks, bibs, sleeve protectors, hats, caps, berets, bonnets, etc.;
F94: - also includes working gloves
F96: This sub-class excludes:
F98: - pins, safety pins, sewing needles, knitting needles, thimbles; rubber gloves and other articles made of rubber; gardening gloves (05.6.1.9);
F100: - protective headgear for sports; other protective gear for sports, such as life jackets, boxing and other sporting gloves, body padding, belts, supports, etc. (09.2.2.1);
F102: - paper handkerchiefs (13.1.2.0);
F104: - watches, jewellery, cuff links, tiepins (13.2.1.1);
F106: - walking sticks and canes, umbrellas and parasols, fans, keyrings (13.2.9.1).
E108: 03.1.3.101 | F108: Ties, handkerchiefs, shawls, scarves, cravats, working gloves and belts including those made of leather | G108: 03.1.3.1 | H108: 03.1.310p | I108: 28238 p 28229 p
E109: 03.1.3.102 | F109: Veils | G109: 03.1.3.1 | H109: 03.1.310p | I109: 28238 p
E110: 03.1.3.103 | F110: Malong | G110: 03.1.3.1 | H110: 03.1.390 p | I110: 28238 p
E111: 03.1.3.104 | F111: Hat, caps, beret and bonnets | G111: 03.1.3.1 | H111: 03.1.390 p | I111: 28229 p
E112: 03.1.3.105 | F112: Braces, aprons, smocks, bibs, sleeve protectors | G112: 03.1.3.1 | H112: 03.1.390 p | I112: 28229 p
E113: 03.1.3.109 | F113: Other articles of clothing and clothing accessories, n.e.c. | G113: 03.1.3.1 | H113: 03.1.390 p | I113: 28229 p
C115: 03.1.3.2 | F115: Clothing accessories (SD)
F117: This subclass includes:
F119: - sewing threads, knitting yarns and accessories for making clothing, such as buckles, buttons, press studs, zip fasteners, ribbons, laces, trimmings, etc.
D121: 03.1.3.21 | F121: Sewing threads
E122: 03.1.3.211 | F122: Cotton sewing thread | G122: =C115 -> 03.1.3.2 | H122: 03.1.330 p | I122: 26350
E123: 03.1.3.212 | F123: Sewing thread of man-made filaments | G123: 03.1.3.2 | H123: 03.1.330 p | I123: 26410
E124: 03.1.3.219 | F124: Other sewing threads, n.e.c. | G124: 03.1.3.2 | H124: 03.1.390 p | I124: 26350 p 26410 p
D126: 03.1.3.22 | F126: Accessories for making clothing
E127: 03.1.3.221 | F127: Buttons | G127: 03.1.3.2 | H127: 03.1.390 p | I127: 28238 p
E128: 03.1.3.222 | F128: Zipper | G128: 03.1.3.2 | H128: 03.1.390 p | I128: 28238 p
E129: 03.1.3.223 | F129: Hook | G129: 03.1.3.2 | H129: 03.1.390 p | I129: 28238 p
E130: 03.1.3.224 | F130: Snap fastener/automatic buttons | G130: 03.1.3.2 | H130: 03.1.390 p | I130: 28238 p
E131: 03.1.3.225 | F131: Garter | G131: 03.1.3.2 | H131: 03.1.390 p | I131: 28238 p
E132: 03.1.3.226 | F132: Buckles | G132: 03.1.3.2 | H132: 03.1.390 p | I132: 28238 p
E133: 03.1.3.227 | F133: Ribbons, laces and trimmings | G133: 03.1.3.2 | H133: 03.1.390 p | I133: 28238 p
E134: 03.1.3.229 | F134: Other accessories for making clothing, n.e.c. | G134: 03.1.3.2 | H134: 03.1.390 p | I134: 28238 p
B136: 03.1.4 | F136: Cleaning, repair, tailoring and hire of clothing (S) | G136: =C136
F137: The cost of materials is included only if the materials are not separately invoiced.
F139: This class includes:
F141: - dry-cleaning, laundering and dyeing of garments;
F143: - darning, mending, repair and altering of garments;
F145: - tailoring services when the customer supplies the material;
F147: - hire of garments.
F149: This class excludes:
F151: - materials, threads, and other accessories purchased by households with the intention of undertaking the repairs themselves (03.1.1.0, 03.1.3.2);
F153: - made-to-measure clothing (03.1.2.1, 03.1.2.2, 03.1.2.3, 03.1.2.4);
F155: - repair of household linen and other household textiles (05.2.2.0);
F157: - dry-cleaning, laundering, dyeing and hire of household linen and other household textiles (05.6.2.9).
C159: 03.1.4.1 | D159: 03.1.4.10 | F159: Cleaning of clothing (S)
E161: 03.1.4.101 | F161: Dry cleaning services (including fur product cleaning services) | G161: =C159 -> 03.1.4.1 | H161: 03.1.411 | I161: 97120
...

Sheet Division 04
A1: Division | B1: Group | C1: Class | D1: Sub-Class | E1: Item | F1: Sub-Item | G1: Description | H1: 2018 UN COICOP | I1: 2009 PCOICOP | J1: CPC 2.1
A3: 04 | G3: DIVISION 04. HOUSING, WATER, ELECTRICITY, GAS AND OTHER FUELS | H3: =D3
G5: Division 04 covers goods and services for the use of the house or dwelling, its maintenance and repair, the supply of water and miscellaneous services related to the dwelling and energy used for heating or cooling. Actual rentals and imputed rentals (according to national accounts (SNA 2008)) for main or secondary residences are classified in Groups 04.1 and 04.2, respectively.
G7: Maintenance, repair and security of the dwelling include materials for repair purchased with the intention of undertaking the repair and maintenance themselves, as well as the repair services purchased from enterprises. It should be noted that only expenditures on materials and services for minor repairs are covered by Group 04.3. Expenditures on materials and services for major maintenance and repair are not part of individual consumption expenditures of households and are thus out of scope of the classification. This refers especially to owner-occupiers; tenants will not make such expenditures on major maintenance and repair at all as they are not the owner of the dwelling.
B9: 04.1 | G9: ACTUAL RENTALS FOR HOUSING | H9: =D9
G11: Rentals normally include payment for the use of the land on which the property stands, the dwelling occupied, the fixtures and fittings for heating, plumbing, lighting, etc., and, in the case of a dwelling let furnished, the furniture.
G13: Rentals also include payment for the use of a garage to provide parking in connection with the dwelling.
G15: The garage does not have to be physically contiguous to the dwelling; nor does it have to be leased from the same landlord.
G17: Rentals do not include payment for the use of garages or parking spaces not providing parking in connection with the dwelling (07.2.4). Nor do they include charges for water supply (04.4.1), refuse collection (04.4.2) and sewage collection (04.4.3); co-proprietor charges for caretaking, gardening, stairwell cleaning, heating and lighting, maintenance of lifts and refuse disposal chutes, etc. in multi-occupied buildings (04.4.4); charges for electricity (04.5.1) and gas (04.5.2); charges for heating and hot water supplied by district heating plants (04.5.5).
G19: Each household has a principal dwelling (sometimes also designated as main or primary home), usually defined with reference to time spent there, whose location defines the country of residence and place of usual residence of this household and of all its members. All other dwellings (owned or leased by the household) are considered secondary dwellings.
G21: This group includes:
G22: - rentals actually paid by tenants or subtenants occupying unfurnished or furnished premises as their main residence.
G24: Includes also:
G25: - payments by households occupying a room in a hotel or boarding house as their main residence.
G27: This group excludes:
G28: - accommodation services of educational establishments and hostels (11.2.0.9);
G29: - retirement homes for elderly persons (13.3.0.2).
C31: 04.1.1 | D31: 04.1.1.0 | G31: Actual rentals paid by tenants for main residence (S)
G33: This class includes:
G34: - rentals actually paid by tenants or subtenants occupying unfurnished or furnished premises as their main residence.
G36: Includes also:
G37: - payments by households occupying a room in a hotel or boarding house as their main residence.
G39: This class excludes:
G40: - garage rentals to provide parking and storage in connection with the dwelling (04.1.2.2);
G41: - accommodation services of educational establishments and hostels (11.2.0.9);
G42: - retirement homes for elderly persons (13.3.0.2).
E44: 04.1.1.01 | G44: Rentals actually paid by tenants or subtenants occupying unfurnished or furnished premises as their main residence.
F45: 04.1.1.011 | G45: Actual rentals paid by tenants or subtenants occupying unfurnished premises as their main residence | H45: 04.1.1.0 | I45: 04.1.110 | J45: 72111p
F46: 04.1.1.012 | G46: Actual rentals paid by tenants or subtenants occupying furnished premises as their main residence | H46: 04.1.1.0 | I46: 04.1.120 | J46: 72111p
E48: 04.1.1.02 | F48: 04.1.1.020 | G48: Payments by households occupying a room in a hotel or boarding house as their main residence. | H48: 04.1.1.0 | I48: 04.1.130 | J48: 72111p
E50: 04.1.1.09 | F50: 04.1.1.090 | G50: Other actual rentals paid by tenants for main residence (S), n.e.c. | H50: 04.1.1.0 | I50: 04.1.190 | J50: 72111p
C52: 04.1.2 | G52: Other actual rentals (S) | H52: =D52
G54: This class includes:
G55: - rentals actually paid for secondary residences;
G56: - rentals of self-storage units;
G57: - garage rentals.
G59: This class excludes:
G60: - accommodation services of holiday villages and holiday centres (11.2.0.2).
D62: 04.1.2.1 | E62: 04.1.2.10 | F62: 04.1.2.100 | G62: Actual rentals paid by tenants for secondary residences (S) | H62: =D62 -> 04.1.2.1 | I62: 04.1.200 | J62: 72111p
D64: 04.1.2.2 | G64: Garage rentals and other rentals paid by tenants (S)
G66: Rental payments for the use of a garage to provide parking and storage in connection with the dwelling. The garage or storage does not have to be physically contiguous to the dwelling, nor does it have to be leased from the same landlord.
G68: This sub-class includes:
G69: - garage rentals in connection with the dwelling;
G70: - rentals of self-storage units.
E72: 04.1.2.21 | F72: 04.1.2.210 | G72: Parking lot payments in connection with the dwelling as main residence | H72: 04.1.2.2 | I72: 04.1.140 | J72: 72112p
E73: 04.1.2.29 | F73: 04.1.2.290 | G73: Other garage rentals and other rentals paid by tenants, n.e.c. | H73: 04.1.2.2 | I73: 04.1.190p | J73: 72112p
B75: 04.2 | G75: IMPUTED RENTALS FOR HOUSING | H75: =D75
G77: Persons who own the dwellings in which they live are treated as owning unincorporated enterprises that produce housing services that are consumed by the household to which the owner belongs. The housing services produced are deemed to be equal in value to the rentals that would be paid on the market for accommodation of the same size, quality and type. The imputed values of the housing services are recorded as final consumption expenditures of the owners.
G79: Imputed rentals normally include value for the use of the land on which the property stands, the dwelling occupied, and the fixtures and fittings for heating, plumbing, lighting, etc. Imputed rentals also include the use of a garage to provide parking in connection with the dwelling. The garage does not have to be physically contiguous to the dwelling.
G81: Imputed rentals do not include payment for the use of garages or parking spaces not providing parking in connection with the dwelling (07.2.4). Nor do they include charges for water supply (04.4.1), refuse collection (04.4.2) and sewage collection (04.4.3); co-proprietor charges for caretaking, gardening, stairwell cleaning, heating and lighting, maintenance of lifts and refuse disposal chutes, etc. in multi-occupied buildings (04.4.4); charges for electricity (04.5.1) and gas (04.5.2); charges for heating and hot water supplied by district heating plants (04.5.5).
C83: 04.2.1 | D83: 04.2.1.0 | E83: 04.2.1.00 | F83: 04.2.1.000 | G83: Imputed rentals of owner-occupiers for main residence (S) | H83: 04.2.1.0 | I83: 04.2.110 04.2.120 | J83: 72111p 72112p
C85: 04.2.2 | D85: 04.2.2.0 | G85: Other imputed rentals (S)
G87: This sub-class includes:
G88: - imputed rentals for secondary residences;
G89: - imputed garage rentals in connection with the dwelling;
G90: - imputed rentals of storage units.
E92: 04.2.2.01 | F92: 04.2.2.010 | G92: Imputed rentals for secondary residences | H92: 04.2.2.0 | I92: 04.2.210 | J92: 72111p 72112p
E93: 04.2.2.02 | F93: 04.2.2.020 | G93: Imputed garage rentals in connection with the dwelling | H93: 04.2.2.0 | I93: 04.2.220p | J93: 72111p 72112p
E94: 04.2.2.03 | F94: 04.2.2.030 | G94: Imputed rentals of storage units | H94: 04.2.2.0 | I94: 04.2.220p | J94: 72111p 72112p
B96: 04.3 | G96: MAINTENANCE, REPAIR AND SECURITY OF THE DWELLING | H96: =D96
G98: Maintenance and repair of dwellings are distinguished by two features: first, they are activities that have to be undertaken regularly in order to maintain the dwelling in good working order; second, they do not change the dwelling’s performance, capacity or expected service life.
G100: There are two types of maintenance and repair of dwellings: those which are minor, such as interior decoration and repairs to fittings, and which are commonly carried out by both tenants and owner-occupiers; and those which are major, such as replastering walls or repairing roofs, and which are carried out by owners only.
G102: Only expenditures which tenants and owner-occupiers incur on materials and services for interior decoration, minor maintenance and repair, that would normally be seen as the responsibility of a tenant, are part of individual consumption expenditure of households.
G104: Expenditure that owners, including owner-occupiers, incur on the decoration, minor repairs and maintenance of the dwelling that would normally be seen as the responsibility of a landlord should not be treated as household final consumption expenditure. The same applies to expenditure which owner-occupiers incur on materials and services for major maintenance and repairs.
G106: Purchases of materials made by tenants or owner-occupiers with the intention of undertaking the maintenance or repair themselves should be shown under Class 04.3.1. If tenants or owner occupiers pay an enterprise to carry out the maintenance or repair, the total value of the service, including the costs of the materials used, should be shown under Class 04.3.2 unless the materials are separately invoiced.
C108: 04.3.1 | G108: Security equipment and materials for the maintenance and repair of the dwelling (ND) | H108: =D108
G110: This class includes:
G111: - products and materials, such as paints and varnishes, renderings, wallpapers, fabric wall coverings, window panes, plaster, cement, putty, wallpaper pastes, etc., purchased for minor maintenance and repair of the dwelling;
G112: - small plumbing items (pipes, taps, joints, etc.), surfacing materials (floorboards, ceramic tiles, etc.) and brushes and scrapers for paint, varnish and wallpaper;
G113: - fitted carpets and linoleum;
G114: - door fittings, power sockets, wiring flex;
G115: - small equipment for surveillance/security for the individual dwelling;
G116: - door phones for dwellings;
G117: - fire extinguishers.
G119: This class excludes:
G120: - hand tools (05.5.2.1);
G121: - lamp bulbs (05.5.2.2);
G122: - brooms, scrubbing brushes, dusting brushes and cleaning products (05.6.1.1);
... G124: - products, materials and fixtures used for major maintenance and repair (intermediate consumption) or for extension and conversion of the dwelling (capital formation).
D126: 04.3.1.1 | G126: Materials for the maintenance and repair of the dwelling (ND)
G128: This sub-class includes:
G129: - products and materials, such as paints and varnishes, renderings, wallpapers, fabric wall coverings, window panes, plaster, cement, putty, wallpaper pastes, etc., purchased for minor maintenance and repair of the dwelling;
G130: - small plumbing items (pipes, taps, joints, etc.), surfacing materials (floorboards, ceramic tiles, etc.) and brushes and scrapers for paint, varnish and wallpaper;
G131: - fitted carpets and linoleum;
G132: - door fittings, power sockets, wiring flex;
G134: This sub-class excludes:
G135: - hand tools (05.5.2.1);
G136: - lamp bulbs (05.5.2.2);
G137: - brooms, scrubbing brushes, dusting brushes and cleaning products (05.6.1.1);
G138: - products, materials and fixtures used for major maintenance and repair (intermediate consumption) or for extension and conversion of the dwelling (capital formation).
E140: 04.3.1.11 | G140: Products and materials, such as paints and varnishes, renderings, wallpapers, fabric wall coverings, window panes, plaster, cement, putty, wallpaper pastes, etc., purchased for minor maintenance and repair of the dwelling
F141: 04.3.1.111 | G141: Paints and varnishes | H141: 04.3.1.1 | I141: 04.3.110 | J141: 35110
F142: 04.3.1.112 | G142: Wallpaper, wall paper pastes and fabric wall covering | H142: 04.3.1.1 | I142: 04.3.120 | J142: 32194
F143: 04.3.1.113 | G143: Plaster | H143: 04.3.1.1 | I143: 04.3.130 | J143: 37410
F144: 04.3.1.114 | G144: Cement | H144: 04.3.1.1 | I144: 04.3.140 | J144: 37330 37430 37440
F145: 04.3.1.115 | G145: Renderings and putty | H145: 04.3.1.1 | I145: 04.3.190p | J145: 37560p
F146: 04.3.1.116 | G146: Window panes | H146: 04.3.1.1 | I146: 04.3.190p | J146: 42120p
F147: 04.3.1.119 | G147: Other | H147: 04.3.1.1 | I147: 04.3.190p | J147: 37560p
E148: 04.3.1.12 | G148: Small plumbing items (pipes, taps, joints, etc.), surfacing materials (floorboards, ceramic tiles, etc.) and brushes and scrapers for paint, varnish and wallpaper
F149: 04.3.1.121 | G149: Small plumbing items (pipes, taps, joints, etc.) | H149: 04.3.1.1 | I149: 04.3.150p | J149: 43240
...

Sheet Completeness(4)
A1: 04.1.110
A2: 04.1.120
A3: 04.1.130
A4: 04.1.190
A5: 04.1.200
A6: 04.1.140
A7: 04.2.110
A8: 04.2.210
A9: 04.2.220
A10: 04.3.110
A11: 04.3.120
A12: 04.3.130
... A55: 04.5.520

Sheet Division 05
A1: Division | B1: Group | C1: Class | D1: Sub-Class | E1: Item | F1: Sub-Item | G1: Description | H1: 2018 UN COICOP | I1: 2009 PCOICOP | J1: CPC 2.1
A3: 05 | G3: DIVISION 05. FURNISHINGS, HOUSEHOLD EQUIPMENT AND ROUTINE HOUSEHOLD MAINTENANCE
G5: Division 05 covers a wide range of products for the equipment of the house or dwelling and the household durables, semi-durables and non-durable as well as some kind of household services. Division 05 includes all kinds of furniture and lightning equipment (05.1), household textiles (05.2), major and smaller electric household appliances (05.3), glassware, tableware and household utensils (05.4), tools and equipment for house and garden (05.5), and goods for the routine household maintenance (05.6).
G7: It also includes repair, installation and rental services of the goods.
G9: Domestic services by paid staff in private service, supplied by enterprises or self-employed persons are included, as well as window cleaning and disinfecting services, dry-cleaning and laundering of household textiles and carpets (05.6.2).
B11: 05.1 | G11: FURNITURE, FURNISHINGS, AND LOOSE CARPETS
C13: 05.1.1 | G13: Furniture, furnishings and loose carpets (D)
G15: This class includes:
G17: - sofas, couches, tables, chairs, cupboards, chests of drawers and bookshelves, hanger stands, coat stands;
G19: - bunk beds, baby furniture, such as cradles, highchairs and play-pens;
G21: - beds, mattresses, base-mattresses, (tatamis), wardrobes, bedside tables;
G23: - kitchen tables and chairs, cupboards and surfaces;
G25: - furniture primarily for bathroom use;
G27: - furniture primarily for gardens use;
G29: - wrought iron benches and tables, arbours;
G31: - small garden houses to store garden tools and machines;
G33: - camping furniture;
G35: - lighting equipment, such as ceiling lights, standard lamps, globe lights and bedside lamps, light and LED strings.
G37: This class also includes:
... G81: - works of art and antique furniture acquired primarily as stores of value (capital formation).
D83: 05.1.1.1 | E83: 05.1.1.10 | G83: Household furniture (D)
F84: 05.1.1.101 | G84: Beds, sofas, couches, cupboards, chest of drawers, bookshelves, tables and chairs (other than kitchen and dining set) | H84: =D83 -> 05.1.1.1 | I84: 05.1.110p | J84: 38111p 38112p 38119p
F85: 05.1.1.102 | G85: Base mattresses, mattresses, (tatamis), bathroom cabinets | H85: 05.1.1.1 | I85: 05.1.150 | J85: 38150p 38140p
F86: 05.1.1.103 | G86: Baby furniture such as cradles, high- chairs and play-pens | H86: 05.1.1.1 | I86: 05.1.160 | J86: 38140p
F87: 05.1.1.104 | G87: Kitchen tables and chairs (dining set) | H87: 05.1.1.1 | I87: 05.1.110p | J87: 38130p 38140p
F88: 05.1.1.105 | G88: Hanger and coat stands | H88: 05.1.1.1 | I88: 05.1.190p | J88: 38140p
F89: 05.1.1.106 | G89: Furniture primarily for bathroom use | H89: 05.1.1.1 | I89: 05.1.150p 05.1.190p | J89: 38140p
F90: 05.1.1.109 | G90: Other household furniture, n.e.c. | H90: 05.1.1.1 | I90: 05.1.190p | J90: 38140p
D92: 05.1.1.2 | E92: 05.1.1.20 | G92: Garden and camping furniture (D)
F93: 05.1.1.201 | G93: Wrought iron benches and tables | H93: 05.1.1.2 | I93: 05.1.170p 05.1.190p | J93: 38140p
F94: 05.1.1.202 | G94: Arbors | H94: 05.1.1.2 | I94: 05.1.170p 05.1.190p | J94: 38140p
F95: 05.1.1.203 | G95: Small garden houses to store garden tools and machines | H95: 05.1.1.2 | I95: 05.1.170p 05.1.190p | J95: 38140p
F96: 05.1.1.209 | G96: Other garden and camping furniture, n.e.c. | H96: 05.1.1.2 | I96: 05.1.170p 05.1.190p | J96: 38140p
D98: 05.1.1.3 | E98: 05.1.1.30 | G98: Lighting equipment (D)
F99: 05.1.1.301 | G99: Ceiling lights | H99: =D98 -> 05.1.1.3 | I99: 05.1.120p | J99: 46531p
F100: 05.1.1.302 | G100: Standard lamps | H100: 05.1.1.3 | I100: 05.1.120p | J100: 46531p
F101: 05.1.1.303 | G101: Globe lights | H101: 05.1.1.3 | I101: 05.1.120p | J101: 46531p
F102: 05.1.1.304 | G102: Lampshade | H102: 05.1.1.3 | I102: 05.1.120p | J102: 46531p
F103: 05.1.1.305 | G103: LED strings | H103: 05.1.1.3 | I103: 05.1.120p | J103: 46539p
F104: 05.1.1.306 | G104: Ring light | H104: 05.1.1.3 | I104: 05.1.120p | J104: 46539p
F105: 05.1.1.309 | G105: Other lighting equipment | H105: 05.1.1.3 | I105: 05.1.120p | J105: 46539p
D107: 05.1.1.4 | E107: 05.1.1.40 | G107: Furnishings, loose carpets and rugs (D)
F108: 05.1.1.401 | G108: Loose carpets and rugs | H108: 05.1.1.4 | I108: 05.1.210 | J108: 27210 27220 27230
F109: 05.1.1.402 | G109: Floor mats | H109: 05.1.1.4 | I109: 05.1.220p | J109: 27290p
F110: 05.1.1.403 | G110: Clocks (wall clocks, alarm clocks, etc.) | H110: 05.1.1.4 | I110: 12.3.121 | J110: 48420
F111: 05.1.1.404 | G111: Pictures, sculptures, engravings, tapestries and other art objects including reproductions of works of art and other ornaments | H111: 05.1.1.4 | I111: 05.1.130 | J111: 32540p 38961p
F112: 05.1.1.405 | G112: Statuettes and other decorative articles of porcelain and crystal glass | H112: 05.1.1.4 | I112: 05.1.190p | J112: 42996p
F113: 05.1.1.406 | G113: Screens, folding partitions and non-textile blinds | H113: 05.1.1.4 | I113: 05.1.140p 05.1.170p | J113: 38140p
F114: 05.1.1.407 | G114: Mirrors, candle-holders or candlesticks | H114: 05.1.1.4 | I114: 05.1.170p | J114: 38140p
F115: 05.1.1.408 | G115: Leather and fur for upholstery and room decorating | H115: 05.1.1.4 | I115: 05.1.190p | J115: 29290p
F116: 05.1.1.409 | G116: Other furnishings, n.e.c. | H116: 05.1.1.4 | I116: 05.1.190p | J116: 27140p
C118: 05.1.2 | D118: 05.1.2.0 | E118: 05.1.2.00 | G118: Repair, installation and hire of furniture, furnishings and loose carpets (S)
G120: The cost of materials is included only if the materials are not separately invoiced.
G122: This subclass includes:
G124: - repair of furniture, furnishings and loose carpets
G126: - restoration of works of art, antique furniture and antique floor coverings other than those acquired primarily as stores of value (capital formation);
G128: - charges for the hire of furniture, furnishings and loose carpets
G130: - charges for the installation of furniture, if charged separately
G132: This subclass excludes:
G134: - laying and repair of fitted carpets, linoleum and other such floor coverings (04.3.2.0);
G136: - separate purchases of materials made by households with the intention of undertaking the repair themselves (05.1.1);
G138: - dry-cleaning and shampooing of carpets (05.6.2.9).
F140: 05.1.2.001 | G140: Repair of furniture | H140: 05.1.2.0 | I140: 05.1.310 | J140: 87240
F141: 05.1.2.002 | G141: Repair of furnishings | H141: 05.1.2.0 | I141: 05.1.320 | J141: 87290p
F142: 05.1.2.003 | G142: Repair of floor coverings | H142: 05.1.2.0 | I142: 05.1.330 | J142: 87290p
F143: 05.1.2.004 | G143: Restoration of work of arts, antique furniture and antique floor covering other than those purchased as stores of value (capital formation) | H143: 05.1.2.0 | I143: 05.1.340 | J143: 87290p
F144: 05.1.2.005 | G144: Charges for the hire of furniture, furnishings and loose carpets | H144: 05.1.2.0 | I144: 05.1.310p | J144: 87390p
F145: 05.1.2.006 | G145: Charges for the installation of furniture | H145: 05.1.2.0 | I145: 05.1.310p | J145: 87390p
B147: 05.2 | G147: HOUSEHOLD TEXTILES
C149: 05.2.1 | G149: Household textiles (SD)
G151: This class includes:
G153: - furnishing fabrics, curtain material, curtains, double curtains, awnings, door curtains and fabric blinds;
G155: - bedding, such as futons, pillows, bolsters and hammocks;
G157: - bed linen, such as sheets, pillowcases, blankets, travelling rugs, plaids, eiderdowns, counterpanes and mosquito nets;
G159: - table linen and bathroom linen, such as tablecloths, table napkins, towels and face clothes;
G161: - other household textiles, such as shopping bags, laundry bags, shoe bags, covers for clothes and furniture, flags, sunshades, etc.;
G163: - oilcloth; bathroom mats, rush mats and doormats, material costs of made to measure household textiles.
G165: This class also includes feather and other fillers for pillows.
G167: This class excludes:
G169: - fabric wall coverings (04.3.1.1);
G171: - floor coverings, such as loose carpets; tapestries (05.1.1.4);
G173: - repair and sewing services of household textiles (05.2.2.0);
... G179: -air mattresses and sleeping bags (09.2.2.2).
D181: 05.2.1.1 | G181: Furnishing fabrics and curtains (SD)
E182: 05.2.1.11 | F182: 05.2.1.110 | G182: Furnishing fabrics | H182: 05.2.1.1 | I182: 05.2.010p | J182: 27130p
E184: 05.2.1.12 | G184: Curtains
F185: 05.2.1.121 | G185: Door curtains | H185: 05.2.1.1 | I185: 05.2.010p | J185: 27130p
F186: 05.2.1.122 | G186: Double curtains | H186: 05.2.1.1 | I186: 05.2.010p | J186: 27130p
F187: 05.2.1.123 | G187: Ready-made curtain | H187: 05.2.1.1 | I187: 05.2.010p | J187: 27130p
F188: 05.2.1.124 | G188: Curtain material | H188: 05.2.1.1 | I188: 05.2.010p | J188: 27130p
F189: 05.2.1.129 | G189: Other curtains | H189: 05.2.1.1 | I189: 05.2.010p | J189: 27130p
E191: 05.2.1.13 | F191: 05.2.1.130 | G191: Awnings and fabric blinds | H191: 05.2.1.1 | I191: 05.2.010p | J191: 27130p
D193: 05.2.1.2 | G193: Bed linen and bedding (SD)
E194: 05.2.1.21 | G194: Bed linen
F195: 05.2.1.211 | G195: Bed sheet | H195: 05.2.1.2 | I195: 05.2.030p | J195: 27120p
F196: 05.2.1.212 | G196: Pillow cases | H196: 05.2.1.2 | I196: 05.2.030p | J196: 27180p
F197: 05.2.1.213 | G197: Blankets | H197: 05.2.1.2 | I197: 05.2.030p | J197: 27110p
F198: 05.2.1.214 | G198: Comforter | H198: 05.2.1.2 | I198: 05.2.030p | J198: 27110p
F199: 05.2.1.215 | G199: Travelling rugs | H199: 05.2.1.2 | I199: 05.2.030p | J199: 27110p
F200: 05.2.1.216 | G200: Plaids, eiderdowns and counterpanes | H200: 05.2.1.2 | I200: 05.2.030p | J200: 27110
...

Sheet Division 06
A1: Division | B1: Group | C1: Class | D1: Sub-Class | E1: Item | F1: Sub-Item | G1: Description | H1: 2018 UN COICOP | I1: 2009 PCOICOP | J1: CPC 2.1
A3: 06 | G3: DIVISION 06. HEALTH | H3: =D3
G5: Division 06 covers four main categories, one of which concerns medicine and health products (06.1), while the three other concern health services. Specifically, outpatient care services that do not require an overnight stay (06.2); inpatient care services provided during an overnight stay (06.3); diagnostic imaging services, medical laboratory services, patient emergency transportation and emergency rescue services (06.4). Medicines and health products (06.1) cover all products that are separately invoiced from health services except when administered under the direct supervision of a health care professional during an overnight stay (06.3). Services and products included in Division 06 are those that can only be used in response to a health need. These services and products aim at preventing the occurrence of illnesses, diseases (e.g. through vaccination); cure from illnesses, diseases, injuries; relieving symptoms of illnesses, diseases, injuries; reduce the severity of illnesses, diseases, injuries; protect against exacerbation and/or complication of illnesses, diseases, injuries; restoring the health status or maintaining/preventing the deterioration of a health condition. The division also includes services provided by health care professional purely for aesthetic beautification purposes (e.g. cosmetic surgery; dental work to whiten teeth). Division 06 excludes food believed to be highly beneficial to health, especially food grown organically as well as foods or food ingredients that have been shown to affect specific functions or system of the body (Division 01).
B7: 06.1 | G7: MEDICINES AND HEALTH PRODUCTS | H7: =D7
G9: This group includes:
G11: - medicines, vaccines, pharmaceutical preparations, medical devices, assistive products and other health-related products used for the prevention, diagnosis and treatment of illnesses, diseases, injuries and purchased by individuals or households, either with or without a prescription, usually from pharmacies, health facilities or medical/assistive equipment suppliers and from Internet reliable sources. They are intended for consumption or use outside a health facility or institution.
G13: This group excludes:
G14: - nutritional supplements and fortified food products (01.1.9.9);
G15: - medicines and health products supplied directly by a health care provider to outpatients (no overnight stay) or inpatients (overnight stay) for consumption outside a health facility or institution are to be classified as outpatient services (06.2) or inpatient services (06.3), if not separately identifiable from the service;
G16: - services fees to dispense medicines charged by a health practitioner during an outpatient service (06.2) or an inpatient service (06.3) if not separately identifiable from the service;
G17: - veterinary products (09.3.2.2);
G18: - products for personal hygiene or personal care including beauty products and creams (13.1) (e.g. aromatherapy products and slimming and beauty enhancing creams).
C20: 06.1.1 | G20: Medicines (ND) | H20: =D20
D22: 06.1.1.1 | G22: Medicines, vaccines and other pharmaceutical preparations (ND)
G24: This sub-class includes:
G25: - all medicines, including branded and generic products to treat illnesses, diseases and injuries;
G26: - pharmaceutical preparations used to treat illnesses, diseases and injuries (e.g. extemporaneous ointments, syrups, capsules or other galenical substances prepared on prescription);
G27: - vaccines, hormones, oral contraceptives and other pharmaceutical products used to prevent, diagnose or treat illnesses, diseases;
G28: - vitamins and minerals;
G29: - alcohol for medical uses, fluids required for dialysis, as well as gases used in health care, such as oxygen, when the patient purchases them directly.
G31: Includes also:
G32: - service fees to dispense medicines charged by the pharmacists.
G34: This sub-class excludes:
G35: - nutritional supplements and fortified food products (01.1.9.9);
G36: - medicines and health products supplied directly by a health care provider to outpatients (no overnight stay) or inpatients (overnight stay) for consumption outside a health facility or institution are to be classified as outpatient services (06.2) or in inpatient services (06.3), if not separately identifiable from the service;
G37: - service fees to dispense medicines charged by a health practitioner during an outpatient service (06.2) or an inpatient service (06.3), if not separately identifiable from the service;
... G39: - products for personal hygiene or personal care including beauty products and creams (13.1) (e.g. aromatherapy products and slimming and beauty enhancing creams).
E41: 06.1.1.11 | F41: 06.1.1.110 | G41: Medicines, branded and generic products, to treat illnesses, diseases and injuries | H41: 06.1.1.1 | I41: 06.1.111p 06.1.112p 06.1.113p 06.1.114p 06.1.115p | J41: 35260p
E43: 06.1.1.12 | G43: Pharmaceutical preparations used to treat illnesses, diseases and injuries (e.g. extemporaneous ointments, syrups, capsules or other galenical substances prepared on prescription)
F44: 06.1.1.121 | G44: Pharmaceutical product used to treat Infections and infestations | H44: 06.1.1.1 | I44: 06.1.111p | J44: 35260p
F45: 06.1.1.122 | G45: Pharmaceutical product used to treat hypertensive and cardiovascular diseases | H45: 06.1.1.1 | I45: 06.1.112p | J45: 35260p
F46: 06.1.1.123 | G46: Pharmaceutical product for pain relief and consciousness such as analgesic, immunology such as anesthetics, and immunosuppresants | H46: 06.1.1.1 | I46: 06.1.113p | J46: 35260p
F47: 06.1.1.124 | G47: Pharmaceutical product used to treat allergies and respiratory diseases | H47: 06.1.1.1 | I47: 06.1.114p | J47: 35260p
F48: 06.1.1.125 | G48: Pharmaceutical product used to treat endocrine diseases and disorders | H48: 06.1.1.1 | I48: 06.1.115p | J48: 35260p
F49: 06.1.1.129 | G49: Other pharmaceutical products to treat illnesses, diseases and injuries, n.e.c. | H49: 06.1.1.1 | I49: 06.1.129p 06.1.192p 06.1.193p 06.1.194p 06.1.195p | J49: 35260p 35290p
E51: 06.1.1.13 | G51: Vaccines, hormones, oral contraceptives and other pharmaceutical products used to prevent, diagnose or treat illnesses, diseases
F53: 06.1.1.131 | G53: COVID-19 vaccines | H53: 06.1.1.1 | I53: 06.1.121p | J53: 35290p
F54: 06.1.1.132 | G54: Other vaccines | H54: 06.1.1.1 | I54: 06.1.121p | J54: 35290p
F55: 06.1.1.133 | G55: Hormones | H55: 06.1.1.1 | I55: 06.1.129p | J55: 35250p
F56: 06.1.1.134 | G56: Oral contraceptives | H56: 06.1.1.1 | I56: 06.1.129p | J56: 35290p
F57: 06.1.1.135 | G57: Injectible contraceptives and other contraceptives, except contraceptive devices | H57: 06.1.1.1 | I57: 06.1.129p | J57: 35290p
F58: 06.1.1.139 | G58: Other pharmaceuical products to prevent, diagnose or treat illnesses and diseases | H58: 06.1.1.1 | I58: 06.1.129 p | J58: 35290p
E60: 06.1.1.14 | F60: 06.1.1.140 | G60: Vitamins and minerals | H60: 06.1.1.1 | I60: 06.1.122 | J60: 35250p
E62: 06.1.1.15 | G62: Alcohol for medical uses, fluids required for dialysis, as well as gases used in health care, such as oxygen, when the patient purchases them directly.
F64: 06.1.1.151 | G64: Alcohol for medical use | H64: 06.1.1.1 | I64: 06.1.129 p 12.1.320p | J64: 34131p 34139p
F65: 06.1.1.152 | G65: Fluids for dialysis | H65: 06.1.1.1 | I65: 06.1.129 p | J65: 35290p
F66: 06.1.1.153 | G66: Gases used in health care, such as oxygen, when the patient purchases them directly | H66: 06.1.1.1 | I66: 06.1.129 p | J66: 34210p
E68: 06.1.1.16 | F68: 06.1.1.160 | G68: Service fees to dispense medicines charged by the pharmacists | H68: 06.1.1.1 | I68: 06.2.390 p | J68: 93199p
E69: 06.1.1.19 | F69: 06.1.1.190 | G69: Other medicines and pharmaceutical preparations | H69: 06.1.1.1 | I69: 06.1.129 p | J69: 35270p
D72: 06.1.1.2 | G72: Herbal medicines and homeopathic products (ND)
G74: This sub-class includes:
G75: - herbal medicines include herbs, herbal materials, herbal preparations and finished herbal products, that contain as active ingredients parts of plants, or other plant materials, or combinations generally used in traditional medicine or complementary medicine;
G76: - homeopathic products include any medicine prepared in accordance with a homeopathic manufacturing procedure described by a pharmacopeia in official use or other officially recognized documents. a homeopathic medicine may contain a number of homeopathic preparations.
G78: This sub-class excludes:
G79: - herbal medicines and homeopathic products supplied directly by a health care provider to outpatients (no overnight stay) or inpatients (overnight stay) for consumption or use outside a health facility are to be classified with outpatient services (06.2)
E81: 06.1.1.21 | F81: 06.1.1.210 | G81: Herbal medicines | H81: 06.1.1.2 | I81: 06.1.191p | J81: 35270p
E82: 06.1.1.22 | F82: 06.1.1.220 | G82: Homeopathic products | H82: 06.1.1.2 | I82: 06.1.191p | J82: 35270p
C85: 06.1.2 | G85: Medical products (ND) | H85: =D85
D87: 06.1.2.1 | E87: 06.1.2.10 | G87: Medical diagnostic products (ND)
G89: This sub-class includes:
G90: - diagnostic equipment for self-test or over the counter sale for personal use outside a health facility or institution;
G91: - pregnancy tests; thermometers, glucose meters, blood pressure meters, and other point of care tests, baby scales, etc.;
G92: - condoms and other mechanical contraceptive devices, masks, medicinal stockings (e.g. compression stockings), medicinal gloves, insecticide treated mosquito nets, etc.;
G93: - inhalers, syringes, humidifiers, nebulizers, hot bags, ice packs, first aid kits, bandages, etc.
G95: Includes also:
G96: - Internet purchases of medical products for personal use.
G98: This sub-class excludes:
G99: - oral contraceptives (06.1.1.1);
G100: - diagnostic products for use inside a health facility or institution (06.3);
G101: - scales (13.1.2.0).
F103: 06.1.2.101 | G103: Pregnancy test kit | H103: 06.1.2.1 | I103: 06.1.200p | J103: 48150p
F104: 06.1.2.102 | G104: Thermometer | H104: 06.1.2.1 | I104: 06.1.200p | J104: 48150p
F105: 06.1.2.103 | G105: Glucose meters | H105: 06.1.2.1 | I105: 06.1.200p | J105: 48150p
F106: 06.1.2.104 | G106: Blood pressure meters | H106: 06.1.2.1 | I106: 06.1.360 | J106: 48150p
F107: 06.1.2.105 | G107: Baby scales | H107: 06.1.2.1 | I107: 06.1.200p | J107: 48150p
F108: 06.1.2.109 | G108: Other medical diagnostic products | H108: 06.1.2.1 | I108: 06.1.200p | J108: 48150p
D110: 06.1.2.2 | E110: 06.1.2.20 | G110: Prevention and protective devices (ND)
G112: This sub-class includes:
G113: - condoms and other mechanical contraceptive devices, masks, medicinal stockings (e.g. compression stockings), medicinal gloves, insecticide treated mosquito nets, etc.
G115: This sub-class excludes:
G116: - oral contraceptives (06.1.1.1).
F118: 06.1.2.201 | G118: Face Masks | H118: 06.1.2.2 | I118: 06.1.129p | J118: 35290p
F119: 06.1.2.202 | G119: Face shields | H119: 06.1.2.2 | I119: 06.1.129p | J119: 35290p
F120: 06.1.2.203 | G120: Medicinal stockings (e.g. compression stockings) | H120: 06.1.2.2 | I120: 06.1.129p | J120: 35290p
F121: 06.1.2.204 | G121: Medicinal gloves | H121: 06.1.2.2 | I121: 06.1.129p | J121: 35290p
F122: 06.1.2.205 | G122: Protective gowns and aprones | I122: 06.1.129p | J122: 35290p
F123: 06.1.2.206 | G123: Insecticide treated mosquito nets | H123: 06.1.2.2 | I123: 06.1.129p | J123: 35290p
F124: 06.1.2.207 | G124: Mechanical contraceptive devices such as condoms | H124: 06.1.2.2 | I124: 06.1.129p | J124: 35290p
F125: 06.1.2.209 | G125: Other prevention and protective devices | H125: 06.1.2.2 | I125: 06.1.129p | J125: 35290p
D128: 06.1.2.3 | E128: 06.1.2.30 | G128: Treatment devices for personal use (ND)
G130: This sub-class includes:
G131: - inhalers, syringes, humidifiers, nebulizers, hot bags, ice packs, first aid kits, bandages, etc.
F133: 06.1.2.301 | G133: Inhalers | H133: 06.1.2.3 | I133: 06.1.200p | J133: 48160p
F134: 06.1.2.302 | G134: Syringes | H134: 06.1.2.3 | I134: 06.1.200p | J134: 48150p
F135: 06.1.2.303 | G135: Humidifiers | H135: 06.1.2.3 | I135: 06.1.200p | J135: 48160p
F136: 06.1.2.304 | G136: Nebulizers | H136: 06.1.2.3 | I136: 06.1.200p | J136: 48160p
F137: 06.1.2.305 | G137: Hot bags, ice packs | H137: 06.1.2.3 | I137: 06.1.200p | J137: 35290p
F138: 06.1.2.306 | G138: First aid kits, bandages | H138: 06.1.2.3 | I138: 06.1.200p | J138: 35290p
F139: 06.1.2.309 | G139: Other treatment devices for personal use | H139: 06.1.2.3 | I139: 06.1.200p | J139: 48150p 48160p
C141: 06.1.3 | G141: Assistive products (D) | H141: =D141
...

Sheet Division 07
A1: Division | B1: Group | C1: Class | D1: Sub-Class | E1: Item | F1: Sub-Item | G1: Description | H1: 2018 UN COICOP | I1: 2009 PCOICOP | J1: CPC 2.1
A3: 07 | G3: DIVISION 07. TRANSPORT | H3: =D3
G5: Division 07 covers four main categories of goods and services for the purpose of transportation: purchase of vehicles (07.1), goods and services for the operation of the personal transport equipment (07.2), passenger transport services (07.3), and transport services of goods (07.4).
G7: Purchase of vehicles covers motor cars, motorcycles, bicycles and animal drawn vehicles. Due to the high share of second-hand motor vehicles in private consumption expenditures, separate subclasses for new and for second-hand motor cars are distinguished.
G9: The second group concerning the operation of personal transport equipment cover parts and accessories for personal transport equipment, fuels and lubricants and the repair and maintenance of personal transport equipment. This group also includes expenditures for parking spaces in garages or in public places, expenditures for tolls and the expenditures to acquire a driving certificate.
G11: Passenger transport services are structured by the mode of transport. However, due to fact that transport tickets may cover more than one mode of transport, a class for the combined passenger transport was created (07.3.6).
G13: The fourth group covers postal and courier services, removal and storage services, and the delivery services of any kinds of goods, if charged separately.
G15: Division 07 does not cover purchases of recreational vehicles, such as camper vans, caravans, trailers, aeroplanes and boats (09.1.2).
B17: 07.1 | G17: PURCHASE OF VEHICLES | H17: =D17
G19: This group includes:
G20: - purchase of vehicles used for transport.
G22: This group excludes:
G23: - purchases of recreational vehicles, such as camper vans, caravans, trailers, aeroplanes and boats (09.1.2).
C25: 07.1.1 | G25: Motor cars (D) | H25: =D25
G27: This class includes:
G28: - motor cars, passenger vans, station wagons, estate cars, SUVs, off-road vehicles, pickup trucks, and the like with either two-wheel drive or four-wheel drive.
G30: Includes also:
G31: - racing motor vehicles and vehicles for shows.
G33: This class excludes:
G34: - invalid carriages (06.1.3.3);
G35: - camper vans (09.1.2.1);
G36: - golf carts (09.1.2.9).
D38: 07.1.1.1 | G38: New motor cars (D)
E39: 07.1.1.11 | G39: Motor cars with combustion engines
F40: 07.1.1.111 | G40: Sedan | H40: 07.1.1.1 | I40: 07.1.100p | J40: 49113p
F41: 07.1.1.112 | G41: Passenger vans, station wagons | H41: 07.1.1.1 | I41: 07.1.100p | J41: 49113p
F42: 07.1.1.113 | G42: SUVs, off-road vehicles | H42: 07.1.1.1 | I42: 07.1.100p | J42: 49113p
F43: 07.1.1.114 | G43: Pickup trucks | H43: 07.1.1.1 | I43: 07.1.100p | J43: 49113p
F44: 07.1.1.119 | G44: Other motor cars | H44: 07.1.1.1 | I44: 07.1.100p | J44: 49113p
E46: 07.1.1.12 | G46: Motor cars with electric engines
F47: 07.1.1.121 | G47: Sedan | H47: 07.1.1.1 | I47: 07.1.100p | J47: 49113p
F48: 07.1.1.122 | G48: Passenger vans, station wagons | H48: 07.1.1.1 | I48: 07.1.100p | J48: 49113p
F49: 07.1.1.123 | G49: SUVs, off-road vehicles | H49: 07.1.1.1 | I49: 07.1.100p | J49: 49113p
F50: 07.1.1.124 | G50: Pickup trucks | H50: 07.1.1.1 | I50: 07.1.100p | J50: 49113p
F51: 07.1.1.129 | G51: Other motor cars | H51: 07.1.1.1 | I51: 07.1.100p | J51: 49113p
E53: 07.1.1.13 | G53: Motor cars with hybrid engines
F54: 07.1.1.131 | G54: Sedan | H54: 07.1.1.1 | I54: 07.1.100p | J54: 49113p
F55: 07.1.1.132 | G55: Passenger vans, station wagons | H55: 07.1.1.1 | I55: 07.1.100p | J55: 49113p
F56: 07.1.1.133 | G56: SUVs, off-road vehicles | H56: 07.1.1.1 | I56: 07.1.100p | J56: 49113p
F57: 07.1.1.134 | G57: Pickup trucks | H57: 07.1.1.1 | I57: 07.1.100p | J57: 49113p
F58: 07.1.1.139 | G58: Other motor cars | H58: 07.1.1.1 | I58: 07.1.100p | J58: 49113p
D60: 07.1.1.2 | E60: 07.1.1.20 | G60: Second-hand motor cars (D)
G62: This sub-class includes:
G63: - used or second-hand motor cars, passenger vans, station wagons, estate cars, SUVs, off-road vehicles, pickup trucks, and the like with either two-wheel drive or four-wheel drive.
G65: Includes also:
G66: - used or second-hand racing motor vehicles and vehicles for shows.
G68: This sub-class excludes:
G69: - invalid carriages (06.1.3.3);
G70: - camper vans (09.1.2.1);
G71: - golf carts (09.1.2.9).
F73: 07.1.1.201 | G73: Sedan | H73: 07.1.1.2 | I73: 07.1.100p | J73: 49113p
F74: 07.1.1.202 | G74: Passenger vans, station wagons | H74: 07.1.1.2 | I74: 07.1.100p | J74: 49113p
F75: 07.1.1.203 | G75: SUVs, off-road vehicles | H75: 07.1.1.2 | I75: 07.1.100p | J75: 49113p
F76: 07.1.1.204 | G76: Pickup trucks | H76: 07.1.1.2 | I76: 07.1.100p | J76: 49113p
F77: 07.1.1.209 | G77: Other motor cars | H77: 07.1.1.2 | I77: 07.1.100p | J77: 49113p
C79: 07.1.2 | D79: 07.1.2.0 | E79: 07.1.2.00 | G79: Motorcycles (D)
G81: This sub-class includes:
G82: - motorcycles of all types, motor scooters and motorized bicycles with combustion engines.
G84: Includes also:
G85: - sidecars;
G86: - used or second-hand motorcycles.
G88: This sub-class excludes:
G89: - e-bikes, pedelecs (07.1.3.0).
F91: 07.1.2.001 | G91: Motor scooters | H91: 07.1.2.0 | I91: 07.1.200 | J91: 49911p 49912p 49913p
F92: 07.1.2.002 | G92: Motorcycles except motor scooters | H92: 07.1.2.0 | I92: 07.1.200 | J92: 49911p 49912p 49913p
F93: 07.1.2.003 | G93: Tricycles (Motorcycle with sidecar) | H93: 07.1.2.0 | I93: 07.1.200 | J93: 49911p 49912p 49913p
F94: 07.1.2.009 | G94: Other | H94: 07.1.2.0 | I94: 07.1.200 | J94: 49911p 49912p 49913p
C96: 07.1.3 | D96: 07.1.3.0 | E96: 07.1.3.00 | G96: Bicycles (D)
G98: This sub-class includes:
G99: - bicycles and tricycles of all types;
G100: - cycle rickshaws;
G101: - e-bikes, pedelecs (electric pedal-assisted bicycles).
G103: This sub-class excludes:
G104: - motorized bicycles with combustion engines (07.1.2.0);
G105: - toy bicycles and tricycles (09.2.1.2);
G106: - bicycles with four wheels (09.1.2.9).
F108: 07.1.3.001 | G108: Bicycles | H108: 07.1.3.0 | I108: 07.1.300p | J108: 49921
F109: 07.1.3.002 | G109: Cycle rickshaws (Pedicab) | H109: 07.1.3.0 | I109: 07.1.300p | J109: 49922
F110: 07.1.3.003 | G110: E-bikes, e-trikes, and pedelecs | H110: 07.1.3.0 | I110: 07.1.300p | J110: 49913p
F111: 07.1.3.009 | G111: Other bicycles | H111: 07.1.3.0 | I111: 07.1.300p | J111: 49921
C113: 07.1.4 | D113: 07.1.4.0 | E113: 07.1.4.00 | F113: 07.1.4.000 | G113: Animal drawn vehicles (D) | H113: 07.1.4.0 | I113: 07.1.400p | J113: 49930p
G115: This sub-class includes:
G116: - animal drawn vehicles;
G117: - animals required to draw the vehicles and related equipment (yokes, collars, harnesses, bridles, reins, etc.).
G119: This sub-class excludes:
G120: - horses and ponies, horse or pony-drawn vehicles and related equipment purchased for recreational purposes (09.1.2.4).
B122: 07.2 | G122: OPERATION OF PERSONAL TRANSPORT EQUIPMENT | H122: =D122
G124: Purchases of parts, accessories or lubricants made by households with the intention of undertaking the maintenance, repair or intervention themselves should be shown under (07.2.1) or (07.2.2). If households pay an enterprise to carry out the maintenance, repair or fitting, the total value of the service, including the costs of the materials used, should be shown under (07.2.3).
C126: 07.2.1 | G126: Parts and accessories for personal transport equipment (SD) | H126: =D126
G128: This class includes:
G129: - tires (new, used or re-treaded), inner tubes, spark plugs, batteries, shock absorbers, filters, pumps and other replacement parts or accessories for personal transport equipment;
G130: - hubcaps, if bought separately;
G131: - baby and children seats for cars, motorcycles and bicycles;
G132: - crash helmets for motorcycles and bicycles;
G133: - fire extinguishers for transport equipment;
G134: - products specifically for the cleaning and maintenance of transport equipment, such as paints, chrome cleaners, sealing compounds and bodywork polishes; covers for motor cars, motorcycles, etc.;
G135: - dash cameras.
G137: Includes also:
G138: - crash helmets with cameras incorporated.
G140: This class excludes:
...

Sheet Division 08
A1: Division | B1: Group | C1: Class | D1: Sub-Class | E1: Item | F1: Sub-Item | G1: Description | H1: 2018 UN COICOP | I1: 2009 PCOICOP | J1: CPC 2.1
A3: 08 | G3: DIVISION 08. INFORMATION AND COMMUNICATION | H3: =D3
G5: Division 08 covers three main groups of goods and services: information and communication equipment, including equipment for the reception, recording and reproduction of sound and vision (08.1), software (08.2), and information and communication services (08.3). Information and communication services include telephone other communication services, Internet access services, TV and radio licences, fee and subscription services, including streaming services of film and music.
G7: Division 08 also includes repair, maintenance and hire of information and communication equipment.
B9: 08.1 | G9: Information and communication equipment | H9: =D9
C11: 08.1.1 | D11: 08.1.1.0 | E11: 08.1.1.00 | G11: Fixed telephone equipment (D)
G13: This sub-class includes:
G14: - telephones, radio-telephones, telefax machines, telephone-answering machines and telephone loudspeakers.
G16: This sub-class excludes:
G17: - telefax and telephone-answering facilities provided by personal computers (08.1.3.1).
F19: 08.1.1.001 | G19: Telephones | H19: 08.1.1.0 | I19: 08.2.020p | J19: 47221p
F20: 08.1.1.002 | G20: Radio-telephones | H20: 08.1.1.0 | I20: 08.2.020p | J20: 47221p
F21: 08.1.1.003 | G21: Telefax machines | H21: 08.1.1.0 | I21: 08.2.030 | J21: 47229p
F22: 08.1.1.004 | G22: Telephone-answering machines | H22: 08.1.1.0 | I22: 08.2.040 | J22: 47229p
F23: 08.1.1.005 | G23: Telephone loudspeakers. | H23: 08.1.1.0 | I23: 08.2.020p | J23: 47229p
F24: 08.1.1.009 | G24: Other fixed telephone equipment | H24: 08.1.1.0 | I24: 08.2.020p | J24: 47229p
C26: 08.1.2 | D26: 08.1.2.0 | G26: Mobile telephone equipment (D)
G28: This sub-class includes:
G29: - mobile telephone handsets, including devices with several functions;
G30: - smartphones.
E32: 08.1.2.01 | F32: 08.1.2.010 | G32: Mobile (cellular) phones | H32: 08.1.2.0 | I32: 08.2.010p | J32: 47222p
E33: 08.1.2.02 | F33: 08.1.2.020 | G33: Smartphones | H33: 08.1.2.0 | I33: 08.2.010p | J33: 47222p
E34: 08.1.2.09 | F34: 08.1.2.090 | G34: Other mobile telephone handsets | H34: 08.1.2.0 | I34: 08.2.010p | J34: 47222p
C37: 08.1.3 | G37: Information processing equipment (D) | H37: =D37
G39: This class includes:
G40: - personal computers, printers, scanners, monitors, projectors, augmented reality (AR) and virtual reality (VR) head mounts, modems, routers, network switches and the like, keyboards, mice, digitizers;
G41: - tablets;
G42: - calculators, including pocket calculators;
G43: - typewriters and word processors (device);
G44: - toner and ink cartridges, laser printer drums, typewriter ribbons.
G46: Includes also:
G47: - telefax and telephone-answering facilities running on computers.
G49: This class excludes:
G50: - computer software packages, such as operating systems, applications, languages, etc. (08.2.0.0);
G51: - video game software; video game computers and consoles (09.2.1.1);
G52: - removable media containing books, dictionaries, encyclopaedias, foreign language trainers, multimedia presentations, etc. in the form of software (09.7.1).
D54: 08.1.3.1 | E54: 08.1.3.10 | G54: Computers, laptops and tablets (D)
G56: This sub-class includes:
G57: - desktop computers and laptops;
G58: - tablets.
G60: Includes also:
G61: - telefax and telephone-answering facilities running on computers.
G63: This sub-class excludes:
G64: - computer software packages, such as operating systems, applications, languages, etc. (08.2.0.0);
G65: - video game software; video game computers and consoles (09.2.1.1);
G66: - removable media containing books, dictionaries, encyclopaedias, foreign language trainers, multimedia presentations, etc. in the form of software (09.7.1).
F68: 08.1.3.101 | G68: Desktop computers | H68: 08.1.3.1 | I68: 09.1.311 | J68: 45230 45240 45250
F69: 08.1.3.102 | G69: Laptop computers | H69: 08.1.3.1 | I69: 09.1.312 | J69: 45220p
F70: 08.1.3.103 | G70: Tablets | H70: 08.1.3.1 | I70: 09.1.319 | J70: 45220p
F71: 08.1.3.109 | G71: Other computers | H71: 08.1.3.1 | I71: 09.1.319 | J71: 45230 45240 45250
D73: 08.1.3.2 | G73: Peripheral equipment and its consumable components (D)
G75: This sub-class includes:
G76: - printers, scanners, monitors, projectors, augmented reality (AR) and virtual reality (VR) head mounts, modems, routers, network switches and the like, keyboards, mice, digitizers;
G77: - typewriters and word processors (device);
G78: - toner and ink cartridges, laser printer drums, typewriter ribbons;
G79: - calculators, including pocket calculators;
G80: - web cameras.
E82: 08.1.3.21 | F82: 08.1.3.210 | G82: Printers | H82: 08.1.3.2 | I82: 09.1.313 | J82: 45263 45264 45265 45266p
E83: 08.1.3.22 | F83: 08.1.3.220 | G83: Scanners | H83: 08.1.3.2 | I83: 09.1.314 | J83: 45262 45266p
E84: 08.1.3.23 | F84: 08.1.3.230 | G84: Monitors | H84: 08.1.3.2 | I84: 09.1.113 | J84: 47314p 47315p
E85: 08.1.3.24 | F85: 08.1.3.240 | G85: Projectors | H85: 08.1.3.2 | I85: 09.1.113 | J85: 47314p 47315p
E86: 08.1.3.25 | G86: Networking equipment
F87: 08.1.3.251 | G87: Network switches | H87: 08.1.3.2 | I87: 09.1.390p | J87: 47223p
F88: 08.1.3.252 | G88: Routers | H88: 08.1.3.2 | I88: 09.1.390p | J88: 47223p
F89: 08.1.3.253 | G89: Modems (include pocket WIFI, home WIFI) | H89: 08.1.3.2 | I89: 09.1.390p | J89: 47223p
F90: 08.1.3.259 | G90: Other networking equipment | H90: 08.1.3.2 | I90: 09.1.390p | J90: 47223p
E91: 08.1.3.26 | G91: Consumable components
F92: 08.1.3.261 | G92: Toner and ink cartridges | H92: 08.1.3.2 | I92: 09.1.390p | J92: 35130p
F93: 08.1.3.262 | G93: Laser printer drums | H93: 08.1.3.2 | I93: 09.1.390p | J93: 35130p
F94: 08.1.3.263 | G94: Printer ribbons | H94: 08.1.3.2 | I94: 09.1.390p | J94: 35130p
F95: 08.1.3.269 | G95: Other consumable components | H95: 08.1.3.2 | I95: 09.1.390p | J95: 35130p
E96: 08.1.3.29 | G96: Other peripheral equipment
F97: 08.1.3.291 | G97: Augmented reality (AR) and virtual reality (VR) head mounts | H97: 08.1.3.2 | I97: 09.1.390p | J97: 46269p
F98: 08.1.3.292 | G98: Keyboards | H98: 08.1.3.2 | I98: 09.1.390p | J98: 45261p
F99: 08.1.3.293 | G99: Mice | H99: 08.1.3.2 | I99: 09.1.390p | J99: 45261p
F100: 08.1.3.294 | G100: Calculators, including pocket calculators | H100: 08.1.3.2 | I100: 09.1.320 | J100: 45130
F101: 08.1.3.295 | G101: Web cameras | H101: 08.1.3.2 | I101: 09.1.390p | J101: 47214p
F102: 08.1.3.299 | G102: Other peripheral equipment, n.e.c. | H102: 08.1.3.2 | I102: 09.1.330 09.1.390p | J102: 45261p 45269p
C104: 08.1.4 | D104: 08.1.4.0 | G104: Equipment for the reception, recording and reproduction of sound and vision (D)
G106: This sub-class includes:
G107: - Television sets, video cassette players and recorders, digital video recorders, DVD players, Blu-ray players, Ultra HD Blue-ray players, streaming boxes, TV aerials of all types;
G108: - radio receivers (radio sets, digital radio sets, Internet radio sets, satellite radio sets, car radios, radio clocks, two-way radios, walkie-talkies, amateur radio receivers and transmitters);
G109: - portable and non-portable CD players;
G110: - portable and non-portable sound players;
G111: - stereo equipment and CD radio cassette recorder;
G112: - turntables, tuners, amplifiers, cassette decks, microphones and speakers, DJ equipment, karaoke systems;
G113: - audio and video systems for cars;
G114: - set-top boxes, satellite receivers, IPTV receivers, TV converter boxes;
G115: - digital media players;
G116: - headphone, earplugs and wireless/Bluetooth headsets
E118: 08.1.4.01 | F118: 08.1.4.010 | G118: Television sets, and TV aerials of all types | H118: 08.1.4.0 | I118: 09.1.112 09.1.119p | J118: 47313p
E119: 08.1.4.02 | F119: 08.1.4.020 | G119: Satellite receivers, IPTV receivers, set-top boxes, TV converter boxes, streaming boxes | H119: 08.1.4.0 | I119: 09.1.199p | J119: 47211p 47212p
E120: 08.1.4.03 | F120: 08.1.4.030 | G120: Digital and cassette video players and recorders such as DVD, Blu-ray, Ultra HD Blue-ray, VHS | H120: 08.1.4.0 | I120: 09.1.121p 09.1.122p 09.1.119p | J120: 47323
E121: 08.1.4.04 | F121: 08.1.4.040 | G121: Radio receivers (radio sets, digital radio sets, Internet radio sets, satellite radio sets, car radios, radio clocks, two-way radios, walkie-talkies, amateur radio receivers and transmitters) | H121: 08.1.4.0 | I121: 09.1.111 | J121: 47311 47312
E122: 08.1.4.05 | F122: 08.1.4.050 | G122: Audio players and recorders such as CD, stereo equipment and radio cassette | H122: 08.1.4.0 | I122: 09.1.121p 09.1.122p 09.1.119p | J122: 47321
E123: 08.1.4.09 | G123: Other equipment for reception, recording and reproduction of sound and vision
F124: 08.1.4.091 | G124: Microphones | H124: 08.1.4.0 | I124: 09.1.191 | J124: 47330p
F125: 08.1.4.092 | G125: Speakers | H125: 08.1.4.0 | I125: 09.1.192 | J125: 47330p
F126: 08.1.4.093 | G126: Headphone, earplugs and wireless/Bluetooth headsets | H126: 08.1.4.0 | I126: 09.1.193 | J126: 47330p
F127: 08.1.4.094 | G127: Amplifiers, karaoke systems | H127: 08.1.4.0 | I127: 09.1.194 09.1.195 | J127: 47330p
...

Sheet Division 09
A1: Group | B1: Class | C1: Sub-Class | D1: Item | E1: Sub-Item | F1: Description | G1: 2018 UN COICOP | H1: 2009 PCOICOP | I1: CPC 2.1
F3: DIVISION 09. RECREATION, SPORT AND CULTURE | G3: =C3
F5: Division 09 covers a wide range of goods and services for recreation, sport and culture and it structured into eight groups. The first group (09.1) covers recreation durables: photographic equipment, other major durables for recreation, such as camper vans, boats, yachts, airplanes and the like). Group 09.2 covers non-major durable recreational goods, such as games and toys, including video game computers, celebration articles, equipment for sport, camping and open-air recreation. The third group (09.3) covers garden products, plants and flowers, the purchases of pets, and expenditures for pets, excluding veterinary services). Recreational services (09.4) cover rental, maintenance and repair of goods classified in Division 09, veterinary and other services for pets, recreational and leisure services, such as amusement parks, games of chance and expenditures for sporting services, both expenditures for practising sports as well as expenditures for attendance of sport events.
F7: Group 09.5 covers cultural goods, such as musical instruments and audio-visual media, followed by cultural services (09.6), which cover cinemas, theatres, concerts, museums, and other cultural sites, as well as photographic services. Whether books or newspapers are in printed or electronic form is irrelevant for classifying them under 09.7.
F9: The last group (09.8) covers package holidays, which as a bundle include all kinds of services, such as transportation, accommodation, foods provision, tour guide, etc. Expenditures for package holiday cannot be split into its components and thus a separate classification category was created. The length of the package holiday and whether the holiday destination is within the home country or outside does not matter.
A11: 09.1 | F11: RECREATIONAL DURABLES | G11: =C11
F12: This group covers recreation durables: photographic equipment, other major durables for recreation, such as camper vans, boats, yachts, aeroplanes and the like).
B14: 09.1.1 | F14: Photographic and cinematographic equipment and optical instruments (D) | G14: =C14
F16: This class includes:
F18: - still cameras, movie cameras and sound-recording cameras, film and slide projectors, enlargers and film processing equipment;
F20: - video cameras, including camcorders, action cameras;
F22: - screens, viewers, lenses (including zoom lenses), lenses, flash attachments, filters, exposure meters, etc.;
F24: - photographic developer and photographic paper;
F26: - binoculars, microscopes, telescopes and compasses
F28: This class also includes:
F30: - separate material purchased by households with the intention of undertaking the repairs themselves;
F32: - photographic and cinematographic films;
F34: - batteries and chargers for cameras and other photographic and cinematographic equipment.
F36: This group excludes:
F38: - dash cameras (07.2.1.3);
F40: - web cameras (08.1.3.2)
C42: 09.1.1.1 | D42: 09.1.1.10 | F42: Cameras (D)
E43: 09.1.1.101 | F43: Still camera (film or digital ) | G43: 09.1.1.1 | H43: 09.1.210 p | I43: 48322 p
E44: 09.1.1.102 | F44: Movie cameras | G44: 09.1.1.1 | H44: 09.1.210 p | I44: 48322 p
E45: 09.1.1.103 | F45: Video cameras, including camcorders, action cameras | G45: 09.1.1.1 | H45: 09.1.210 p | I45: 48322 p
E46: 09.1.1.104 | F46: Drones with cameras | G46: 09.1.1.1 | H46: 09.1.299 p | I46: 48321 p
E47: 09.1.1.105 | F47: Film and slide projectors | G47: 09.1.1.1 | H47: 09.1.299 p | I47: 48321 p
E48: 09.1.1.106 | F48: Enlargers and film processing equipment | G48: 09.1.1.1 | H48: 09.1.220 p | I48: 48329 p
E49: 09.1.1.109 | F49: Other cameras, n.e.c. | G49: 09.1.1.1 | H49: 09.1.210 p 09.1.299 p | I49: 48321 p 48322 p
C51: 09.1.1.2 | D51: 09.1.1.20 | F51: Accessories for photographic and cinematographic equipment (D)
E52: 09.1.1.201 | F52: Screens | G52: 09.1.1.2 | H52: 09.1.220 p | I52: 48329 p 48353 p
E53: 09.1.1.202 | F53: Lenses (including zoom lenses) | G53: 09.1.1.2 | H53: 09.1.220 p | I53: 48329 p 48353 p
E54: 09.1.1.203 | F54: Filters and exposure meters | G54: 09.1.1.2 | H54: 09.1.220 p | I54: 48329 p 48353 p
E55: 09.1.1.204 | F55: Photographic developer and photographic paper | G55: 09.1.1.2 | H55: 09.1.220 p | I55: 48329 p 48353 p
E56: 09.1.1.205 | F56: Photographic and cinematographic films | G56: 09.1.1.2 | H56: 09.1.220 p | I56: 48322 p 48329 p 48353 p
E57: 09.1.1.206 | F57: Camera specific batteries and chargers | G57: 09.1.1.2 | H57: 09.1.220 p | I57: 48329 p 48353 p
E58: 09.1.1.209 | F58: Other accessories for photographic and cinematographic equipment, n.e.c. | G58: 09.1.1.2 | H58: 09.1.291 p | I58: 48329 p 48353 p
C60: 09.1.1.3 | D60: 09.1.1.30 | F60: Optical instruments (D)
E61: 09.1.1.301 | F61: Binoculars | G61: 09.1.1.3 | H61: 09.1.230 p | I61: 48314 p
E62: 09.1.1.302 | F62: Microscopes | G62: 09.1.1.3 | H62: 09.1.230 p | I62: 48314 p
E63: 09.1.1.303 | F63: Telescopes | G63: 09.1.1.3 | H63: 09.1.230 p | I63: 48314 p
E64: 09.1.1.309 | F64: Other optical instruments, n.e.c. | G64: 09.1.1.3 | H64: 09.1.230 p | I64: 48314 p
B66: 09.1.2 | F66: Major durables for recreation (D) | G66: =C66
F68: This class includes:
F70: - camper vans, caravans and trailers
F72: - aeroplanes, microlight aircraft, gliders, hang gliders and hot-air balloons
F74: - boats, yachts, outboard motors, sails, rigging and superstructures
F76: - vessels for recreation, sailboats, sailboards, water sport boards
F78: - canoes, kayaks, windsurfing boards
F80: - sea diving equipment
F82: - horses and ponies, horse or pony-drawn vehicles, camels and dromedaries, purchased for recreational purposes and related equipment (harnesses, bridles, reins, saddles, etc.)
F84: - golf carts
F86: - large steel-frame swimming pools for the garden
F88: - billiard tables, ping-pong tables, pinball machines, gaming machines, etc.
F90: - other major durables for recreation n.e.c.
... F99: - inflatable boats, rafts and swimming pools for children and the beach (09.2.2.2)
C101: 09.1.2.1 | D101: 09.1.2.10 | F101: Camper vans, caravans and trailers (D)
E102: 09.1.2.101 | F102: Camper vans | G102: 09.1.2.1 | H102: 09.2.110 p | I102: 49113 p
E103: 09.1.2.102 | F103: Caravans | G103: 09.1.2.1 | H103: 09.2.110 p | I103: 49113 p
E104: 09.1.2.103 | F104: Trailers | G104: 09.1.2.1 | H104: 09.2.110 p | I104: 49113 p 49222 p
C106: 09.1.2.2 | D106: 09.1.2.20 | F106: Airplanes, microlight aircraft, gliders, hang gliders and hot-air balloons (D)
E107: 09.1.2.201 | F107: Airplanes | G107: 09.1.2.2 | H107: 09.2.120 p | I107: 49622 p
E108: 09.1.2.202 | F108: Microlight aircraft | G108: 09.1.2.2 | H108: 09.2.120 p | I108: 49623 p
E109: 09.1.2.203 | F109: Gliders | G109: 09.1.2.2 | H109: 09.2.120 p | I109: 49610 p
E110: 09.1.2.204 | F110: Hang gliders | G110: 09.1.2.2 | H110: 09.2.120 p | I110: 49610 p
E111: 09.1.2.205 | F111: Hot-air balloons | G111: 09.1.2.2 | H111: 09.2.120 p | I111: 49610 p
C113: 09.1.2.3 | D113: 09.1.2.30 | F113: Boats, yachts, outboard motors and other water sport equipment (D)
E114: 09.1.2.301 | F114: Boats and sailboats | G114: 09.1.2.3 | H114: 09.2.130 p | I114: 49410 p 49490 p
E115: 09.1.2.302 | F115: Yachts | G115: 09.1.2.3 | H115: 09.2.130 p | I115: 49410 p 49490 p
E116: 09.1.2.303 | F116: Outboard motors | G116: 09.1.2.3 | H116: 09.2.130 p | I116: 49410 p 49490 p
E117: 09.1.2.304 | F117: Sailboards, water sport boards and wind surfing boards | G117: 09.1.2.3 | H117: 09.2.130 p | I117: 49410 p 49490 p
E118: 09.1.2.305 | F118: Kayaks and canoes | G118: 09.1.2.3 | H118: 09.2.130 p | I118: 49410 p 49490 p
E119: 09.1.2.306 | F119: Jet ski | G119: 09.1.2.3 | H119: 09.2.130 p | I119: 49410 p 49490 p
E120: 09.1.2.307 | F120: Rigging and superstructures | G120: 09.1.2.3 | H120: 09.2.130 p | I120: 49410 p 49490 p
E121: 09.1.2.308 | F121: Sea diving equipment | G121: 09.1.2.3 | H121: 09.2.130 p | I121: 49410 p 49490 p
E122: 09.1.2.309 | F122: Other water sport equipment, n.e.c. | G122: 09.1.2.3 | H122: 09.2.130 p | I122: 49410 p 49490 p
C124: 09.1.2.4 | D124: 09.1.2.40 | F124: Horses, ponies, camel and dromedaries and accessories (D)
E125: 09.1.2.401 | F125: Horses and ponies | G125: 09.1.2.4 | H125: 09.2.140 p | I125: 02131 p
E126: 09.1.2.402 | F126: Horses drawn vehicles | G126: 09.1.2.4 | H126: 09.2.140 p | I126: 02131 p
E127: 09.1.2.403 | F127: Harnesses | G127: 09.1.2.4 | H127: 09.2.140 p | I127: 29210 p
E128: 09.1.2.404 | F128: Bridles | G128: 09.1.2.4 | H128: 09.2.140 p | I128: 29290 p
E129: 09.1.2.405 | F129: Reins | G129: 09.1.2.4 | H129: 09.2.140 p | I129: 29290 p
E130: 09.1.2.406 | F130: Saddles | G130: 09.1.2.4 | H130: 09.2.140 p | I130: 29210 p
E131: 09.1.2.409 | F131: Others | G131: 09.1.2.4 | H131: 09.2.140 p | I131: 29210 p
C133: 09.1.2.9 | D133: 09.1.2.90 | F133: Other major durables for recreation (D)
E134: 09.1.2.901 | F134: Golf carts | G134: 09.1.2.9 | H134: 09.2.190 p | I134: 38440 p
E135: 09.1.2.902 | F135: Billiard and ping-pong tables | G135: 09.1.2.9 | H135: 09.2.220 p | I135: 38590 p
E136: 09.1.2.903 | F136: Pinball and gaming machines | G136: 09.1.2.9 | H136: 09.2.220 p | I136: 38590 p
E137: 09.1.2.904 | F137: Scooters | G137: 09.1.2.9 | H137: 09.2.190 p | I137: 38440 p
E138: 09.1.2.905 | F138: Bicycles with guide wheels | G138: 09.1.2.9 | H138: 09.2.190 p | I138: 49921 p
E139: 09.1.2.909 | F139: Other major durables for recreation, n.e.c. | G139: 09.1.2.9 | H139: 09.2.190 p | I139: 38590 p
A141: 09.2 | F141: OTHER RECREATIONAL GOODS | G141: =C141
B143: 09.2.1 | F143: Games, toys and hobbies (SD) | G143: =C143
F145: This class includes:
F147: - card games, board games, parlour games, chess sets and the like
F149: - video-game software; video-game computers that plug into a television set; video-game cassettes and video-game CD-ROMs, video-game downloads
F151: - game apps
F153: - gamepads, joysticks, racing wheels and other accessories for video gaming
F155: - electronic games
F157: - toys of all kinds including dolls, soft toys, toy cars and trains, toy bicycles and tricycles, toy construction sets, puzzles, modelling clay, electronic games, masks, disguises, jokes, novelties, fireworks and rockets, festoons and holiday decorations
...

Sheet Division 10
A1: Group | B1: Class | C1: Sub-Class | D1: Item | E1: Sub-Item | F1: Description | G1: 2018 UN COICOP | H1: 2009 PCOICOP | I1: CPC 2.1
F3: DIVISION 10. EDUCATION SERVICES | G3: =C3
F5: Division 10 covers educational services only. The focus of Groups 10.1 to 10.4 is on formal education (that leads to degrees, certificates, or diplomas), except for non-formal and informal education e.g., Alternative Learning System (ALS). It includes education by radio or television broadcasting as well as modular, e-learning, blended learning and correspondence courses. It includes admission and registration fees as well as tuition fees.
F7: It includes other education related fees, such as camps and field trips, course fees, diploma fees, examination fees, graduation fees, laboratory fees, physical education fees, capital assessment fees, homeschool fees, etc.
F9: - Homeschool fees are expenditure or tuition fees from home-based education services (from early childhood education services up to upper secondary education services) provided by homeschool provider who are offerring home-based schooling.
F10: - Tuition fees are expenditure from school-based education services provided by public or private schools.
F12: The breakdown of educational services is based upon the level categories of the 2011 revision of the International Standard Classification of Education (ISCED 2011) of the United Nations Educational, Scientific and Cultural Organization (UNESCO) and the 2017 Philippine Standard Classification of Education (PSCED) of PSA.
F14: This Division does not include expenditures on other education related goods and services, such as:
F16: - school uniforms (03.1.2.4);
F17: - education support services, such as health-care services (06);
F18: - transport services except in the case of excursions which are part of the normal school programme (07.3.2.3);
F19: - stationery (09.7.4.0);
F20: - catering services (11.1.2.1);
F21: - accommodation services (11.2.0.3).
A23: 10.1 | F23: EARLY CHILDHOOD AND PRIMARY EDUCATION | G23: =C23
G24: =C24
B25: 10.1.0 | F25: Early chilhood and primary education (S)
F27: This clas includes:
F28: - levels 0 and 1 of ISCED 2011 and 2017 PSCED Early childhood and primary education;
F29: - literacy programmes for students too old for primary school;
F30: - education services for children with special educational needs.
F32: Includes also:
F33: - excursions which are part of the normal school programme (travel and accommodation costs).
F35: This class excludes:
F36: - child care services without educational programme (13.3.0.1).
C38: 10.1.0.1 | F38: Early childhood education services (S)
F40: This sub-class includes:
F41: - level 0 of ISCED 2011: Early childhood education is designed primarily to support children’s early cognitive, physical, social and emotional development and introduce very young children to organized instruction outside of the family context. Programmes are designed for children below the entry age to primary education and are typically centre, school-based or other institutionalized for a group of children (e.g. community-based, home-based). This education may also be provided in hospitals or in special schools or training centres;
F42: - special education services for children with special educational needs
F44: Includes also:
F45: - excursions which are part of the normal school programme (travel and accommodation costs).
F47: This sub-class excludes:
F48: - child care services without educational programme (13.3.0.1).
D50: 10.1.0.11 | F50: Public early childhood educational development programs
F52: These include expenditures on early childhood education program provided by public institutions except for special groups (i.e., I.P learner, learners with dissability).
E54: 10.1.0.111 | F54: Tuition fees | G54: 10.1.0.1 | H54: 10.1.111p | I54: 92100
E55: 10.1.0.112 | F55: Allowance for family member/s studying away from home | G55: 10.1.0.1 | H55: 10.1.112p | I55: 92100
E56: 10.1.0.119 | F56: Other educational expenses | G56: 10.1.0.1 | H56: 10.1.119p | I56: 92100
D58: 10.1.0.12 | F58: Private early childhood educational development programs
F60: These include expenditures on early childhood education program provided by private institutions except for special groups (i.e., I.P learner, learners with dissability).
E62: 10.1.0.121 | F62: Tuition fees | G62: 10.1.0.1 | H62: 10.1.121p | I62: 92100
E63: 10.1.0.122 | F63: Allowance for family member/s studying away from home | G63: 10.1.0.1 | H63: 10.1.122p | I63: 92100
E64: 10.1.0.123 | F64: Homeschool fees | G64: 10.1.0.1 | H64: 10.1.129p | I64: 92100
E65: 10.1.0.129 | F65: Other educational expenses | G65: 10.1.0.1 | H65: 10.1.129p | I65: 92100
D67: 10.1.0.13 | F67: Public early childhood educational development programs for special groups
F69: These include expenditures on early childhood education program for children belonging in indigenous and muslim groups, or with special needs such as the gifted, mentally, psycho-socially and differently-abled in public institutions.
E71: 10.1.0.131 | F71: Tuition fees | G71: 10.1.0.1 | H71: 10.1.131p | I71: 92100
E72: 10.1.0.132 | F72: Allowance for family member/s studying away from home | G72: 10.1.0.1 | H72: 10.1.132p | I72: 92100
E73: 10.1.0.139 | F73: Other educational expenses | G73: 10.1.0.1 | H73: 10.1.139p | I73: 92100
D75: 10.1.0.14 | F75: Private early childhood educational development programs for special groups
F77: These include expenditures on early childhood education program for children belonging in indigenous and muslim groups, or with special needs such as the gifted, mentally, psycho-socially and differently-abled in private institutions.
E79: 10.1.0.141 | F79: Tuition fees | G79: 10.1.0.1 | H79: 10.1.141p | I79: 92100
E80: 10.1.0.142 | F80: Allowance for family member/s studying away from home | G80: 10.1.0.1 | H80: 10.1.142p | I80: 92100
E81: 10.1.0.143 | F81: Homeschool fees | G81: 10.1.0.1 | H81: 10.1.149p | I81: 92100
E82: 10.1.0.149 | F82: Other educational expenses | G82: 10.1.0.1 | H82: 10.1.149p | I82: 92100
D84: 10.1.0.15 | F84: Public pre-primary education programs (kindergarten)
F86: These include expenditures on pre-primary education programs (kindergarten) provided by public institutions except for special groups (i.e., I.P learner, learners with dissability).
E88: 10.1.0.151 | F88: Tuition fees | G88: 10.1.0.1 | H88: 10.1.111p | I88: 92100
E89: 10.1.0.152 | F89: Allowance for family member/s studying away from home | G89: 10.1.0.1 | H89: 10.1.112p | I89: 92100
E90: 10.1.0.159 | F90: Other educational expenses | G90: 10.1.0.1 | H90: 10.1.119p | I90: 92100
D92: 10.1.0.16 | F92: Private pre-primary education programs (kindergarten)
F94: These include expenditures on pre-primary education programs (kindergarten) provided by private institutions except for special groups (i.e., I.P learner, learners with dissability).
E96: 10.1.0.161 | F96: Tuition fees | G96: 10.1.0.1 | H96: 10.1.121p | I96: 92100
E97: 10.1.0.162 | F97: Allowance for family member/s studying away from home | G97: 10.1.0.1 | H97: 10.1.122p | I97: 92100
E98: 10.1.0.163 | F98: Homeschool fees | G98: 10.1.0.1 | H98: 10.1.129p | I98: 92100
E99: 10.1.0.169 | F99: Other educational expenses | G99: 10.1.0.1 | H99: 10.1.129p | I99: 92100
D101: 10.1.0.17 | F101: Public pre-primary education programs (kindergarten) for special groups
F103: These include expenditures on pre-primary education programs (kindergarten) for children belonging in indigenous and muslim groups, or with special needs such as the gifted, mentally, psycho-socially and differently-abled in public institutions.
E105: 10.1.0.171 | F105: Tuition fees | G105: 10.1.0.1 | H105: 10.1.131p | I105: 92100
E106: 10.1.0.172 | F106: Allowance for family member/s studying away from home | G106: 10.1.0.1 | H106: 10.1.132p | I106: 92100
E107: 10.1.0.179 | F107: Other educational expenses | G107: 10.1.0.1 | H107: 10.1.139p | I107: 92100
D109: 10.1.0.18 | F109: Private pre-primary education programs (kindergarten) for special groups
F111: These include expenditures on pre-primary education programs (kindergarten) for children belonging in indigenous and muslim groups, or with special needs such as the gifted, mentally, psycho-socially and differently-abled in private institutions.
E113: 10.1.0.181 | F113: Tuition fees | G113: 10.1.0.1 | H113: 10.1.141p | I113: 92100
E114: 10.1.0.182 | F114: Allowance for family member/s studying away from home | G114: 10.1.0.1 | H114: 10.1.142p | I114: 92100
E115: 10.1.0.183 | F115: Homeschool fees | G115: 10.1.0.1 | H115: 10.1.149p | I115: 92100
E116: 10.1.0.189 | F116: Other educational expenses | G116: 10.1.0.1 | H116: 10.1.149p | I116: 92100
C118: 10.1.0.2 | F118: Primary education (S)
F120: This sub-class includes:
F121: - level 1 of ISCED 2011 and 2017 PSCED: The legal age of entry in Primary education is not below 5 years old nor above 6 years old and generally lasts for 6 years and will lasts until age 11. Programmes are normally designed to provide students with fundamental skills in reading, writing and mathematics and establish a solid foundation for learning and understanding core areas of knowledge and personal and social development;
F122: - organized instruction for children with special needs and literacy or basic skills programmes within or outside the school system which are similar in content to programme in primary education;
F123: - literacy programmes for students too old for primary school;
F124: - excursions which are part of the normal school programme (travel and accommodation costs).
D126: 10.1.0.21 | F126: Public primary education services
F128: These include expenditures on primary education services provided by public institutions except for special groups (i.e., I.P learner, learners with dissability) and continuing/second-chance education.
E130: 10.1.0.211 | F130: Tuition fees | G130: 10.1.0.2 | H130: 10.1.211 | I130: 92200
E131: 10.1.0.212 | F131: Allowance for family member/s studying away from home | G131: 10.1.0.2 | H131: 10.1.212 | I131: 92200
E132: 10.1.0.219 | F132: Other educational expenses | G132: 10.1.0.2 | H132: 10.1.219p | I132: 92200
D134: 10.1.0.22 | F134: Private primary education services
F136: These include expenditures on primary education services provided by private institutions except for special groups (i.e., I.P learner, learners with dissability) continuing/second-chance education.
E138: 10.1.0.221 | F138: Tuition fees | G138: 10.1.0.2 | H138: 10.1.221 | I138: 92200
E139: 10.1.0.222 | F139: Allowance for family member/s studying away from home | G139: 10.1.0.2 | H139: 10.1.222 | I139: 92200
E140: 10.1.0.223 | F140: Homeschool fees | G140: 10.1.0.2 | H140: 10.1.229p | I140: 92200
E141: 10.1.0.229 | F141: Other educational expenses | G141: 10.1.0.2 | H141: 10.1.229p | I141: 92200
D143: 10.1.0.23 | F143: Public primary education services for special groups
F145: These include expenditures on primary education services for children belonging in indigenous and muslim groups, or wirh special needs such as the gifted, mentally, psycho-socially and differently-abled in public institutions.
E147: 10.1.0.231 | F147: Tuition fees | G147: 10.1.0.2 | H147: 10.1.231 | I147: 92200
E148: 10.1.0.232 | F148: Allowance for family member/s studying away from home | G148: 10.1.0.2 | H148: 10.1.232 | I148: 92200
E149: 10.1.0.239 | F149: Other educational expenses | G149: 10.1.0.2 | H149: 10.1.239p | I149: 92200
D151: 10.1.0.24 | F151: Private primary education services for special groups
...

Sheet Division 11
A1: Group | B1: Class | C1: Sub-Class | D1: Item | E1: Sub-Item | F1: Description | G1: 2018 UN COICOP | H1: 2009 PCOICOP | I1: CPC 2.1
F3: DIVISION 11. RESTAURANTS AND ACCOMMODATION SERVICES | G3: =C3
F5: Division 11 covers food and beverage serving services provided by restaurants, cafés and similar facilities, either with full, limited, or self-service, or by canteens, cafeterias or refectories at work or school and other educational establishment’s premises (11.1). The distinction between full service and limited service relates to the range of the food and beverage serving services: a service by waiters to the individual customer seated at tables will be qualified to be a full service.
F7: Accommodation (11.2) this Division includes services for visitors and other travellers away from their principal or secondary residence. If not separately invoiced, it also includes food and beverage services and other serving services, such as housekeeping, parking, laundry, swimming pools and exercise rooms, recreational facilities and conference and convention facilities.
F9: This excludes permanent principal or secondary residence accommodation (Division 04).
A11: 11.1 | F11: FOOD AND BEVERAGE SERVING SERVICES | G11: =C11
B13: 11.1.1 | F13: Restaurants, café and the like (S) | G13: =C13
F15: Food and beverages services provided by restaurants, cafés and similar eating facilities either providing full, limited, or self-service.
F17: This class includes:
F19: - tobacco that is consumed with a shisha or hookah pipes in restaurants, cafés, or shisha lounges;
F21: - narcotics purchased in coffee shops, if service charge is applied;
F23: - tips and gratuities.
F25: This class excludes:
F27: - food and beverage provided by supermarkets and markets and consumed at their premises (related products in Division 01);
F29: - food products and beverages dispensed by automatic vending machines not as a delivery service provided restaurants, cafés, buffets, bars, tearooms and similar facilities (01.1.9.1);
F31: - tobacco purchases (02.3.0);
F33: - food and beverage services on public transport, if not separately invoiced (07.3);
F35: - food and beverages delivery services, if separately invoiced (07.4.9.2);
F37: - dancing establishments and nightclubs entrance fees (09.4.6.1);
... F43: - food and beverage services provided by hotels or other lodging establishments, if not separately invoiced from accommodation (11.2).
C45: 11.1.1.1 | D45: 11.1.1.10 | F45: Restaurants, café and the like - with full service (S)
F47: Food and beverages services provided by restaurants, cafés and similar eating facilities providing full service consisting of waiter service to individual customers seated at tables, with or without entertainment.
F49: This sub-class also includes:
F51: - food and beverages provided by full-service facilities mainly serving drinks: cafés, buffets, bars, tearooms and similar;
F53: - food and beverages provided by full-service restaurants, cafés and the like and consumed off their premises; food and beverages provided by full-service restaurants, cafés and the like and home-delivered;
F55: - food and beverage full-services in hotels or other accommodation establishments, if separately invoiced from accommodation;
F57: - food and beverage full-services in establishments providing recreational, cultural, sporting or entertainment services (theatres, cinemas, sports stadiums, swimming pools, sports complexes, museums, art galleries, nightclubs, dancing establishments and similar facilities) if separately invoiced;
F59: - tobacco that is consumed with a shisha or hookah pipes in restaurants, cafés, or shisha lounges;
F61: - narcotics purchased in coffee shops, if service charge is applied;
F63: - tips and gratuities.
F65: This sub-class excludes:
F67: - food and beverage provided by supermarkets and markets and consumed at their premises (related products in Division 01);
F69: - tobacco purchases (02.3.0);
... F81: - food and beverage services in hotels or other lodging establishments, if not separately invoiced from accommodation (11.2).
E83: 11.1.1.101 | F83: Restaurants | G83: 11.1.1.1 | H83: 11.1.111p | I83: 63310
E84: 11.1.1.102 | F84: Cafes | G84: 11.1.1.1 | H84: 11.1.111p | I84: 63310p
E85: 11.1.1.103 | F85: Hotels, if food and beverages are separately invoiced | G85: 11.1.1.1 | H85: 11.2.010 | I85: 63310p
E86: 11.1.1.104 | F86: Other accommodation establishments, if separately invoiced from accommodation | G86: 11.1.1.1 | H86: 11.1.190p | I86: 63310p
E87: 11.1.1.105 | F87: Establishments providing recreational, cultural, sporting or entertainment services (e.g. theatres, cinemas, sports stadiums, swimming pools, sports complexes, museums, art galleries, nightclubs, dancing establishments and similar facilities) | G87: 11.1.1.1 | H87: 11.1.112p | I87: 63310p
E88: 11.1.1.106 | F88: Shisha lounge and the like with full service | G88: 11.1.1.1 | H88: 11.1.112p | I88: 63310p
E89: 11.1.1.109 | F89: Other establishments providing food and beverage in full service, n.e.c. | G89: 11.1.1.1 | H89: 11.1.190p | I89: 63393p
C92: 11.1.1.2 | D92: 11.1.1.20 | F92: Restaurants, café and the like - with limited service (S)
F94: Food and beverages serving services provided by limited and self-service facilities i.e. without waiter service and with or without seating
F96: This sub-class includes:
F98: - food and beverage services provided by self-service restaurants;
F100: - food and beverages provided by refreshment stands, fish and chip stands, fast-food outlets without seating and take-away facilities;
F102: - food products and beverages prepared on the premises and dispensed through automatic vending machines as a delivery service in a self-service restaurant or similar (e.g. automat restaurants);
F104: - food and beverage for immediate consumption provided by kiosks, food stalls, food carts, street vendors and the like.
F106: - ice-cream parlours and cake serving places;
F108: - food and beverages provided by catering contractors whether collected by the customer or delivered to the customer’s home;
F110: - food and beverage services on public transport (coaches, trains, boats, aeroplanes, etc.), if separately invoiced;
F112: - tobacco that is consumed with a shisha or hookah pipes in restaurants, cafés, or shisha lounges;
F114: - narcotics purchased in coffee shops, if service charge is applied
F116: - tips and gratuities.
... F136: - food and beverage services in hotels or other lodging establishments, if not separately invoiced from accommodation (11.2).
E138: 11.1.1.201 | F138: Self service restaurant and cafes | G138: 11.1.1.2 | H138: 11.1.111p | I138: 63320p
E139: 11.1.1.202 | F139: Refreshment stands, fish and chip stands, fast-food outlet | G139: 11.1.1.2 | H139: 11.1.190p | I139: 63320p
E140: 11.1.1.203 | F140: Kiosks, food stalls, and food carts | G140: 11.1.1.2 | H140: 11.1.120 | I140: 63320p
E141: 11.1.1.204 | F141: Ice cream parlors and cake serving places | G141: 11.1.1.2 | H141: 11.1.190p | I141: 63320p
E142: 11.1.1.205 | F142: Public transport (coaches, trains, boats, airplanes, etc.) | G142: 11.1.1.2 | H142: 11.1.113 | I142: 63320p
E143: 11.1.1.206 | F143: Catering contractors whether collected by the customer or delivered to the customer’s home | G143: 11.1.1.2 | H143: 11.1.140 | I143: 63392p
E144: 11.1.1.207 | F144: Shisha lounge and the like with limited service | G144: 11.1.1.2 | H144: 11.1.112p | I144: 63399p
E145: 11.1.1.209 | F145: Other food and beverage services provided in limited service, n.e.c. | G145: 11.1.1.2 | H145: 11.1.190p | I145: 63399p
B147: 11.1.2 | F147: Canteens, cafeterias and refectories (S) | G147: =C147
F149: Food and beverages provided by canteens, cafeterias or refectories i.e. restaurants, cafés and the like, at work/office premises, in schools, universities and other educational establishments, to hospital in-patients, if separately invoiced.
F151: This also include university refectories, military messes and wardrooms.
F153: This class excludes:
F155: - food and beverages provided by schools, university and other educational establishments, if not separately invoiced (10.1 - 10.5);
F157: - food and beverages provided to hospital in-patients, if not separately invoiced (06.3).
C159: 11.1.2.1 | D159: 11.1.2.10 | F159: Canteens, cafeterias of universities, schools, and kindergartens (S)
F161: Food and beverages provided by canteens, cafeterias or refectories i.e. restaurants, cafés and the like, at schools, universities and other educational establishments.
F163: This also include kindergarten canteens, school canteens, and university refectories.
F165: This excludes food and beverages provided by schools, university and other educational establishments, if not separately invoiced (10.1 - 10.5).
E167: 11.1.2.101 | F167: Kindergarten canteens | G167: 11.1.2.1 | H167: 11.1.210 | I167: 63393p
E168: 11.1.2.102 | F168: School canteens | G168: 11.1.2.1 | H168: 11.1.210 | I168: 63393p
E169: 11.1.2.103 | F169: University cafeterias/ refectories | G169: 11.1.2.1 | H169: 11.1.220 | I169: 63393p
E170: 11.1.2.109 | F170: Other food and beverage services provided in kindergarten canteens, school canteens, and university refectories, n.e.c. | G170: 11.1.2.9 | H170: NEW | I170: 63393p
C172: 11.1.2.9 | D172: 11.1.2.90 | F172: Other canteens, cafeterias and refectories (S)
F174: Food and beverages provided by canteens, cafeterias or refectories i.e. restaurants, cafés and the like at work/office premises, to hospital in-patients, if separately invoiced.
F176: This also include military messes and wardrooms.
F178: This sub-class excludes food and beverages provided to hospital in-patients if not separately invoiced (06.3).
E180: 11.1.2.901 | F180: Military messes/wardrooms | G180: 11.1.2.9 | H180: 11.1.220p | I180: 63399p
E181: 11.1.2.902 | F181: Work/office premises | G181: 11.1.2.9 | H181: 11.1.210 | I181: 63399p
E182: 11.1.2.909 | F182: Other canteens, cafeterias and refectories, n.e.c. | G182: 11.1.2.9 | H182: 11.1.220p 11.1.210p | I182: 63399p
A185: 11.2 | F185: ACCOMMODATION SERVICES | G185: =C185
B187: 11.2.0 | F187: Accommodation services (S)
F189: Accommodation services for visitors and other travellers away from their permanent principal or secondary residence. It includes other services, if not separately invoiced, such as: food and beverage services, housekeeping, parking, laundry, swimming pools and exercise rooms, recreational facilities and conference and convention facilities.
F191: This class includes:
F193: - resorts, hotels, hotels letting rooms by the hour, motels, inns and pensions;
F195: - accommodation services provided by private, holiday homes, guesthouses and boarding houses as secondary residence and other “bed and breakfast” establishments;
F197: - time-share units;
F199: - holiday villages and holiday centres, camping, onsite (non-mobile) caravans and boats;
F201: - youth hostels and mountain refuges;
F203: - bungalows, chalets, housekeeping cottages and cabins;
F205: - student residences, school and other educational establishments dormitories, when separately invoiced; hostels and other accommodations for workers;
F207: - railway sleeping cars and other public transport, when separately invoiced;
F208: - website fees to list, find, and rent lodging;
F210: - travel agency fees for accommodation if priced separately;
... F226: - housing in orphanages, homes for disabled or maladjusted persons (13.3.0.2).
C228: 11.2.0.1 | D228: 11.2.0.10 | F228: Hotels, motels, inns and similar accommodation services (S)
...

Sheet Division 12
A1: Group | B1: Class | C1: Sub-Class | D1: Item | E1: Sub-Item | F1: Description | G1: 2018 UN COICOP | H1: 2009 PCOICOP | I1: CPC 2.1
F3: DIVISION 12. INSURANCE AND FINANCIAL SERVICES | G3: =C3
F5: Division 12 covers insurance (12.1) and financial services (12.2). Insurance and financial services are provided by financial corporations. These may be paid for explicitly or implicitly. Some transactions in financial assets may also involve both explicit and implicit charges. Implicit charges are not always as evident as the way in which charges are made for most goods and services and are typically calculated using a number of observable transactions. Examples of implicit charges arise from the financial services provided in association with interest charges on loans and deposits, the acquisition and disposal of financial assets and liabilities in financial markets, and insurance and pension schemes. The imputed values of expenditure on insurance and financial services are not directly observable from household income and expenditure surveys.
F7: Insurance services are subdivided by type of insurance. Financial services are subdivided by financial intermediation services indirectly measured and by the other forms of actual and indirect charges and remittance fees for financial services. For the definition and the measurement of the insurance and financial services specific national accounts concepts (2008 SNA) do apply.
A9: 12.1 | F9: INSURANCE | G9: =C9
F11: Service charges for insurance are classified by type of insurance, namely: life insurance and non-life insurance (that is, insurance in connection with the dwelling, health, transport, etc.). Service charges for multi-risk insurance covering several risks should be classified on the basis of the cost of the principal risk if it is not possible to allocate the service charges to the various risks covered.
F13: The basic method for measuring the service charge for non-life insurance is total premiums earned plus investment income earned from investing the premiums less adjusted claims incurred.
F15: The basic method for measuring the service charge for life insurance is premiums earned plus investment income earned from investing the premiums less benefits due less increases (plus decreases) in life insurance technical reserves.
B17: 12.1.1 | C17: 12.1.1.0 | F17: Life and accident insurance (S)
F19: This sub-class includes:
F21: - service charges for life insurance, annuities, death benefit insurance, education insurance, etc.
F23: Includes also:
F25: - service charges for funeral insurance;
F27: - service charges for accident insurance.
D29: 12.1.1.01 | E29: 12.1.1.010 | F29: Service charges for life insurance | G29: 12.1.1.0 | H29: 12.5.110p | I29: 71311
D30: 12.1.1.02 | E30: 12.1.1.020 | F30: Service charges for death benefit insurance | G30: 12.1.1.0 | H30: 12.5.120p | I30: 71311
D31: 12.1.1.03 | E31: 12.1.1.030 | F31: Service charges for education insurance | G31: 12.1.1.0 | H31: 12.5.130 | I31: 71311
D32: 12.1.1.04 | E32: 12.1.1.040 | F32: Service charges for annuities | G32: 12.1.1.0 | H32: NEW | I32: 71311
D33: 12.1.1.05 | E33: 12.1.1.050 | F33: Service charges for funeral insurance | G33: 12.1.1.0 | H33: 12.5.110p 12.5.120p | I33: 71311
D34: 12.1.1.06 | E34: 12.1.1.060 | F34: Service charges for accident insurance | G34: 12.1.1.0 | H34: 12.5.110p 12.5.120p | I34: 71311
B36: 12.1.2 | C36: 12.1.2.0 | F36: Insurance connected with health (S)
F38: This sub-class includes:
F40: - service charges for direct sickness insurance;
F42: - service charges for social health insurance;
F43: - service charges for disability insurance;
F45: - service charges for critical illness insurance;
F46: - service charges for long-term care insurance;
F48: - service charges for supplementary health insurance;
F50: - service charges for supplementary prescription drug insurance;
F52: - service charges for travel health insurance.
F54: Includes also:
F56: - service charges for medical transport (e.g. ambulance) insurance.
D58: 12.1.2.01 | E58: 12.1.2.010 | F58: Service charges for direct sickness insurance | G58: 12.1.2.0 | H58: 12.5.300p | I58: 71322
D59: 12.1.2.02 | E59: 12.1.2.020 | F59: Service charges for social health insurance | G59: 12.1.2.0 | H59: 12.5.300p | I59: 71322
D60: 12.1.2.03 | E60: 12.1.2.030 | F60: Service charges for disability insurance | G60: 12.1.2.0 | H60: 12.5.300p | I60: 71322
D61: 12.1.2.04 | E61: 12.1.2.040 | F61: Service charges for critical illness insurance | G61: 12.1.2.0 | H61: 12.5.300p | I61: 71322
D62: 12.1.2.05 | E62: 12.1.2.050 | F62: Service charges for long-term care insurance | G62: 12.1.2.0 | H62: 12.5.300p | I62: 71322
D63: 12.1.2.06 | E63: 12.1.2.060 | F63: Service charges for supplementary health insurance | G63: 12.1.2.0 | H63: 12.5.300p | I63: 71322
D64: 12.1.2.07 | E64: 12.1.2.070 | F64: Service charges for supplementary prescription drug insurance | G64: 12.1.2.0 | H64: 12.5.300p | I64: 71322
D65: 12.1.2.08 | E65: 12.1.2.080 | F65: Service charges for travel health insurance | G65: 12.1.2.0 | H65: 12.5.300p | I65: 71322
D66: 12.1.2.09 | E66: 12.1.2.090 | F66: Other insurance connected with health | G66: 12.1.2.0 | H66: 12.5.300p | I66: 71322
B68: 12.1.3 | C68: 12.1.3.0 | F68: Insurance connected with the dwelling (S)
F70: This sub-class includes:
F72: - service charges paid by owner-occupiers and by tenants for the kinds of insurance typically taken out by tenants against fire, theft, water damage, etc.;
F73: - service charges for household contents insurance.
F75: This sub-class excludes:
F77: - service charges paid by owner-occupiers for the kinds of insurance typically taken out by landlords (intermediate consumption).
D80: 12.1.3.01 | E80: 12.1.3.010 | F80: Service charges paid by owner-occupiers and by tenants for the kinds of insurance typically taken out by tenants against fire, theft, water damage, etc | G80: 12.1.3.0 | H80: 12.5.200p | I80: 71334
D81: 12.1.3.02 | E81: 12.1.3.020 | F81: Service charges for household contents insurance | G81: 12.1.3.0 | H81: 12.5.200p | I81: 71334
B83: 12.1.4 | F83: Insurance connected with transport (S)
F85: This class includes:
F87: - service charges for insurance in respect of personal transport equipment;
F89: - service charges for travel insurance (for change of travel plans, travel cancellation, etc.) and luggage insurance.
C91: 12.1.4.1 | F91: Personal transport insurance (S)
F93: This sub-class includes:
F95: - service charges for car insurance;
F97: - service charges for insurance in respect of personal transport equipment;
F99: - service charges for insurances covering civil liability or damage to third parties or their property arising from the operation of personal transport equipment.
F101: Includes also:
F103: - service charges for insurance in respect of bikes, motorcycles, boats, yachts, sailboats, aeroplanes, etc.
D105: 12.1.4.11 | E105: 12.1.4.110 | F105: Service charges for car insurance | G105: 12.1.4.1 | H105: 12.5.500p | I105: 71331
D106: 12.1.4.12 | E106: 12.1.4.120 | F106: Service charges for insurance in respect of personal transport equipment | G106: 12.1.4.1 | H106: 12.5.500p | I106: 71332
D107: 12.1.4.13 | E107: 12.1.4.130 | F107: Service charges for insurances covering civil liability or damage to third parties or their property arising from the operation of personal transport equipment | G107: 12.1.4.1 | H107: 12.5.500p | I107: 71332
D108: 12.1.4.14 | E108: 12.1.4.140 | F108: Service charges for insurance in respect of bikes, motorcycles, boats, yachts, sailboats, aeroplanes, etc | G108: 12.1.4.1 | H108: 12.5.500p | I108: 71332
C110: 12.1.4.2 | D110: 12.1.4.20 | E110: 12.1.4.200 | F110: Travel insurance (S) | G110: =C110 -> 12.1.4.2 | H110: 12.5.420 | I110: 71337
F112: This sub-class includes:
F114: - service charges for travel insurance (for change of travel plans, travel cancellation, etc.) and luggage insurance.
F116: This sub-class excludes:
F118: - travel health insurance (12.1.2.0).
B120: 12.1.9 | C120: 12.1.9.0 | F120: Other insurance (S)
F122: This sub-class includes:
F124: - service charges for other insurance, such as civil liability for injury or damage to third parties or their property;
F126: - service charges for standardized guarantees;
F127: - service charges for legal insurance;
F129: - service charges for pet medical insurance.
F131: This sub-class excludes:
F133: - civil liability or damage to third parties or their property arising from the operation of personal transport equipment (12.1.4.1).
D135: 12.1.9.01 | E135: 12.1.9.010 | F135: Service charges for other insurance, such as civil liability for injury or damage to third parties or their property | G135: 12.1.9.0 | H135: 12.5.500p | I135: 71335
D136: 12.1.9.02 | E136: 12.1.9.020 | F136: Service charges for standardized guarantees | G136: 12.1.9.0 | H136: 12.5.500p | I136: 71339
D137: 12.1.9.03 | E137: 12.1.9.030 | F137: Service charges for legal insurance | G137: 12.1.9.0 | H137: 12.5.500p | I137: 71339
D138: 12.1.9.04 | E138: 12.1.9.040 | F138: Service charges for pet medical insurance | G138: 12.1.9.0 | H138: 12.5.500p | I138: 71322
A140: 12.2 | F140: FINANCIAL SERVICES | G140: =C140
F142: Financial services are subdivided by financial intermediation services indirectly measured and by the other forms of actual and implicit charges and remittance fees for financial services.
B144: 12.2.1 | C144: 12.2.1.0 | F144: Financial intermediation services indirectly measured (S)
F146: This sub-class includes:
F148: - financial intermediation services indirectly measured of deposit taking corporations.
F150: Deposit-taking corporations are the following: 1) central bank, 2) universal/commercial banks (includes specialized government banks and money market unit investment trust funds), 3) thrift banks (includes microfinance-oriented banks), 4) rural banks (includes microfinance-oriented banks), 5) cooperative banks, 6) non-stock savings and loan associations (NSSLAs), and 7) non-bank with quasi-banking functions (NBQBs).
F152: Includes also:
F154: - implicit financial services provided by other financial corporations (i.e., credit card agencies, pawnshops, government finance institutions, offshore banking units, lending companies (for example, in providing student loans and import/export loans), captive financial institutions, and moneylenders) that carry out lending activities.
D156: 12.2.1.01 | E156: 12.2.1.010 | F156: Financial intermediation services indirectly measured of deposit taking corporations | G156: 12.2.1.0 | H156: 12.6.100p | I156: 71599
D158: 12.2.1.02 | F158: Implicit financial services provided by other financial corporations (i.e., credit card agencies, pawnshops, government finance institutions, offshore banking units, lending companies (for example, in providing student loans and import/export loans), captive financial institutions, and moneylenders) that carry out lending activities.
E159: 12.2.1.021 | F159: Implicit financial services provided by moneylenders | G159: 12.2.1.0 | H159: 12.6.100p | I159: 71599
E160: 12.2.1.022 | F160: Implicit financial services provided by credit card issuers | G160: 12.2.1.0 | H160: 12.6.100p | I160: 71599
E161: 12.2.1.023 | F161: Implicit financial services provided by finance associates of retailers who may be responsible for providing loans | G161: 12.2.1.0 | H161: 12.6.100p | I161: 71599
E162: 12.2.1.024 | F162: Implicit financial services provided by pawnshops and corporations involved in lending | G162: 12.2.1.0 | H162: 12.6.100p | I162: 71599
E163: 12.2.1.025 | F163: Implicit financial services provided by e-wallet application that provide loans | G163: 12.2.1.0 | H163: 12.6.100p | I163: 71599
E164: 12.2.1.029 | F164: Other implicit financial services | G164: 12.2.1.0 | H164: 12.6.100p | I164: 71599
B166: 12.2.2 | C166: 12.2.2.0 | D166: 12.2.2.00 | E166: 12.2.2.000 | F166: Explicit charges by deposit-taking corporations (S) | G166: 12.2.2.0 | H166: 12.6.210p | I166: 71599
F168: This sub-class includes:
F170: - actual charges for the financial services of deposit-taking corporations, such as 1) central bank, 2) universal/commercial banks (includes specialized government banks and money market unit investment trust funds), 3) thrift banks (includes microfinance-oriented banks), 4) rural banks (includes microfinance-oriented banks), 5) cooperative banks, 6) non-stock savings and loan associations (NSSLAs), and 7) non-bank with quasi-banking functions (NBQBs).
...

Sheet Division 13
A1: Group | B1: Class | C1: Sub-Class | D1: Item | E1: Sub-Item | F1: Description | G1: 2018 UN COICOP | H1: 2009 PCOICOP | I1: CPC 2.1
F3: DIVISION 13. PERSONAL CARE, SOCIAL PROTECTION AND MISCELLANEOUS GOODS AND SERVICES | G3: =C3
F5: Division 13 covers goods and services for personal care (13.1), jewellery and watches (13.2), services of social protection (13.3), and all other services for households, which are not classified elsewhere (13.9). Goods and services for personal care cover electric and non-electric appliances for personal care as well as hairdressing services. Goods of personal effects cover jewellery and watches, celebration and devotional articles, and travel goods and articles.
F7: Social protection services cover child-care, non-medical retirement homes for elderly persons and disabled persons, services to maintain persons in their private homes and related service. Group 13.9 cover all the other services for households, which are not classified elsewhere, such as fees for legal and administrative services, fees for real estate agencies, charges for undertaking, payment for various personal services (e.g. graphologists, bodyguards, matrimonial agencies, etc.)
F9: This division also includes religious services.
A11: 13.1 | F11: PERSONAL CARE | G11: =C11
B13: 13.1.1 | F13: Electric appliances for personal care (SD) | G13: =C13
F15: This class includes:
F17: - electric razors, hair trimmers and epilators, hand-held and hood hairdryers, straightening irons, curling tongs and styling combs, sunlamps, vibrators, electric toothbrushes and other electric appliances for dental hygiene, etc.;
F19: - repair of electric appliances for personal care.
C21: 13.1.1.1 | D21: 13.1.1.10 | E21: 13.1.1.100 | F21: Electric appliances for personal care (SD) | G21: =C21 -> 13.1.1.1 | H21: 12.1.210 | I21: 44816 p
F23: This includes the purchases of electric razors, hair trimmers and epilators, hand-held and hood hairdryers, straightening irons, curling tongs and styling combs, sunlamps, vibrators, electric toothbrushes and other electric appliances for dental hygiene, etc.
F25: This sub-class excludes repair of electric appliances for personal care (13.1.1.2).
C27: 13.1.1.2 | D27: 13.1.1.20 | E27: 13.1.1.200 | F27: Repair of electric appliances for personal care (S) | G27: =C27 -> 13.1.1.2 | H27: 12.1.220 | I27: 87151 p
F29: The cost of materials is included only if the materials are not separately invoiced.
F31: This also includes repair of electric appliances for personal care.
B33: 13.1.2 | C33: 13.1.2.0 | F33: Other appliances, articles and products for personal care (ND)
F35: This sub-class includes:
F37: - non-electric appliances: shavers, razors and hair trimmers and blades therefor, scissors, nail files, combs, shaving brushes, hairbrushes, toothbrushes, nail brushes, hairpins, curlers, personal weighing machines, scales, etc.;
F39: - articles for personal hygiene: toilet soap, medicinal soap, cleansing oil and milk, shaving soap, shaving cream and foam, toothpaste, epilation wax, paper handkerchiefs, etc.;
F41: -beauty products: lipstick, nail varnish, make-up and make-up removal products (including powder compacts, brushes and powder puffs), hair lacquers and lotions, pre-shave and after-shave products, sunbathing products and sunscreens, hair removers, perfumes and toilet waters, personal deodorants, bath products, etc.
F43: This sub-class excludes:
F45: - handkerchiefs made of fabric (03.1.3.1);
F47: - diapers for the aging population (06.1.3.3);
F49: - baby scales (06.1.2.1).
D51: 13.1.2.01 | F51: Purchase of non-electric appliances (razors and hair trimmers and blades therefor, scissors, nail files, combs, shaving brushes, hairbrushes, toothbrushes, nail brushes, hairpins, curlers, personal weighing machines, baby scales, etc.)
E52: 13.1.2.011 | F52: Razors, hair trimmers, blades and scissors | G52: 13.1.2.0 | H52: 12.1.310p | I52: 42913 p 44816 p
E53: 13.1.2.012 | F53: Nail files and nail brushes | G53: 13.1.2.0 | H53: 12.1.310p | I53: 42915 p
E54: 13.1.2.013 | F54: Combs and hairbrushes | G54: 13.1.2.0 | H54: 12.1.310p | I54: 38994 p
E55: 13.1.2.014 | F55: Toothbrushes | G55: 13.1.2.0 | H55: 12.1.310p | I55: 38993 p
E56: 13.1.2.015 | F56: Hairpins and curlers | G56: 13.1.2.0 | H56: 12.1.310p | I56: 38994 p
E57: 13.1.2.016 | F57: Personal weighing machines | G57: 13.1.2.0 | H57: 12.1.310p | I57: 43922 p
E58: 13.1.2.019 | F58: Other non-electric appliances | G58: 13.1.2.0 | H58: 12.1.310p | I58: 38999 p
D59: 13.1.2.02 | F59: Purchase of articles for personal hygiene (toilet and medicinal soap, cleansing oil and milk, shaving soap, shaving cream and foam, toothpaste and mouthwash, shampoo and hair conditioner, etc.)
E60: 13.1.2.021 | F60: Toilet and medicinal soap | G60: 13.1.2.0 | H60: 12.1.320p | I60: 35321 p
E61: 13.1.2.022 | F61: Facial wash, cleansing oil and milk, facial scrub | G61: 13.1.2.0 | H61: 12.1.320p | I61: 38999 p
E62: 13.1.2.023 | F62: Shaving soap, cream and foam | G62: 13.1.2.0 | H62: 12.1.320p | I62: 35321 p
E63: 13.1.2.024 | F63: Toothpaste | G63: 13.1.2.0 | H63: 12.1.320p | I63: 38999 p
E64: 13.1.2.025 | F64: Mouthwash | G64: 13.1.2.0 | H64: 12.1.320p | I64: 38999 p
E65: 13.1.2.026 | F65: Shampoo and hair conditioner | G65: 13.1.2.0 | H65: 12.1.320p | I65: 35323 p
E66: 13.1.2.027 | F66: Hand sanitizer | G66: 13.1.2.0 | H66: 12.1.320p | I66: 35323 p
E67: 13.1.2.028 | F67: Feminine and masculine wash | G67: 13.1.2.0 | H67: 12.1.320p | I67: 35323 p
E68: 13.1.2.029 | F68: Other articles for personal hygiene | G68: 13.1.2.0 | H68: 12.1.320p | I68: 38999 p
D69: 13.1.2.03 | F69: Purchase of beauty products (lipsticks, nail varnishes, make-up and make-up removal products (including powder compacts, brushes and powder puffs), hair lacquers and lotions, pre-shave and after-shave products, sunbathing products, hair removers, perfumes and toilet waters, personal deodorants, bath products, etc.)
E70: 13.1.2.031 | F70: Lipsticks and lip tints | G70: 13.1.2.0 | H70: 12.1.330 | I70: 35323 p
E71: 13.1.2.032 | F71: Nail varnishes | G71: 13.1.2.0 | H71: 12.1.330 | I71: 35323 p
E72: 13.1.2.033 | F72: Make-up and make-up removal products | G72: 13.1.2.0 | H72: 12.1.330 | I72: 35323 p
E73: 13.1.2.034 | F73: Hair lacquers and lotions | G73: 13.1.2.0 | H73: 12.1.330 | I73: 35323 p
E74: 13.1.2.035 | F74: Sunbathing products | G74: 13.1.2.0 | H74: 12.1.330 | I74: 35323 p
E75: 13.1.2.036 | F75: Perfumes | G75: 13.1.2.0 | H75: 12.1.330 | I75: 35323 p
E76: 13.1.2.037 | F76: Personal deodorants and tawas | G76: 13.1.2.0 | H76: 12.1.330 | I76: 35323 p
E77: 13.1.2.039 | F77: Other beauty products | G77: 13.1.2.0 | H77: 12.1.330 | I77: 35323 p
D78: 13.1.2.09 | F78: Other appliances, articles and products for personal care (ND) n.e.c.
E79: 13.1.2.091 | F79: Disposable Diaper | G79: 13.1.2.0 | H79: 12.1.390 | I79: 32196 p
E80: 13.1.2.092 | F80: Cloth Diaper | G80: 13.1.2.0 | H80: 12.1.390 | I80: 32196 p
E81: 13.1.2.093 | F81: Wipes | G81: 13.1.2.0 | H81: 12.1.390 | I81: 32196 p
E82: 13.1.2.094 | F82: Toilet paper, sanitary towels, and facial tissue | G82: 13.1.2.0 | H82: 12.1.390 | I82: 32193 p 32131 p
E83: 13.1.2.095 | F83: Sanitary napkins and tampons | G83: 13.1.2.0 | H83: 12.1.390 | I83: 32193 p
E84: 13.1.2.096 | F84: Cotton wools and cotton buds | G84: 13.1.2.0 | H84: 12.1.390 | I84: 35270 p
E85: 13.1.2.097 | F85: Bath sponge | G85: 13.1.2.0 | H85: 12.1.390 | I85: 35323 p
E86: 13.1.2.099 | F86: Other appliances, articles and products for personal care (ND) n.e.c. | G86: 13.1.2.0 | H86: 12.1.390 | I86: 38999 p
B88: 13.1.3 | F88: Hairdressing salons and personal grooming establishments (S) | G88: =C88
F90: This class includes:
F92: - services of hairdressing salons, barbers, beauty shops, manicures, pedicures, Turkish baths, saunas, solariums, non-medical massages, etc.;
F94: - body care, depilation and the like, diet clubs, tattoo and piercing services.
F96: This class excludes:
F98: - spas for medical purpose (06.2, 06.3);
F100: - animals tattooing (09.4.5.0);
F102: - fitness centres (09.4.6.2).
C104: 13.1.3.1 | D104: 13.1.3.10 | F104: Hairdressing (S)
F106: This includes services of hairdressing salons or barbers for women, men and children.
E108: 13.1.3.101 | F108: Hairdressing services in salons/parlors including hot oil, rebonding, cold wave/perm, hair trim, etc. | G108: 13.1.3.1 | H108: 12.1.110 p | I108: 97210 p
E109: 13.1.3.102 | F109: Hairdressing services in barber shops | G109: 13.1.3.1 | H109: 12.1.120 | I109: 97210 p
E110: 13.1.3.109 | F110: Other hairdressing services n.e.c. | G110: 13.1.3.1 | H110: 12.1.190 p | I110: 97210 p
C112: 13.1.3.2 | D112: 13.1.3.20 | F112: Personal grooming treatments (S)
F114: This sub-class includes:
F116: - facial beauty treatments, depilation, solarium, pedicure, body care, manicure, thalassotherapy, Turkish baths, saunas, non-medical massages, etc.;
F118: - diet clubs, tattoo and piercing services.
F120: This sub-class excludes:
F122: - spas for medical purpose (06.2, 06.3);
F124: - animals tattooing (09.4.5.0);
F126: - fitness centres (09.4.6.2).
E128: 13.1.3.201 | F128: Facial beauty treatment | G128: 13.1.3.2 | H128: 12.1.190 p | I128: 97290 p
E129: 13.1.3.202 | F129: Manicure/pedicure | G129: 13.1.3.2 | H129: 12.1.110 p | I129: 97220
E130: 13.1.3.203 | F130: Spas, saunas, Turkish baths, solariums, non-medical massages, etc. | G130: 13.1.3.2 | H130: 12.1.130 | I130: 97230 p
E131: 13.1.3.209 | F131: Other personal grooming treatments n.e.c. | G131: 13.1.3.2 | H131: 12.1.190 p | I131: 97290 p
A134: 13.2 | F134: OTHER PERSONAL EFFECTS | G134: =C134
B136: 13.2.1 | C136: 13.2.1.1 | F136: Jewellery and watches (D)
F138: This sub-class includes:
F140: - precious stones and metals and jewellery fashioned out of such stones and metals;
F142: - costume jewellery, cuff links and tiepins;
F144: - watches, stopwatches;
F146: - repair, remodelling and hire of jewellery and watches.
F148: This sub-class excludes:
F150: - wall clocks, floor clocks, alarm clocks, travel clocks (05.1.1.4);
F152: - ornaments (05.1.1.4, 05.4.0.1);
F154: - radio clocks (08.1.4.0);
F156: - smartwatches (08.1.9.1);
F158: - precious stones and metals and jewellery fashioned out of such stones and metals acquired primarily as stores of value (capital formation).
D160: 13.2.1.11 | F160: Jewellery
...

Sheet Division 14
A1: Group | B1: Class | C1: Sub-Class | D1: Item | E1: Sub-Item | F1: Description | G1: 2018 UN COICOP | H1: 2009 PCOICOP | I1: CPC 2.1
F3: DIVISION 14. INDIVIDUAL CONSUMPTION EXPENDITURE OF NON-PROFIT INSTITUTIONS SERVING HOUSEHOLDS (NPISHs)
A5: 14.1 | F5: HOUSING
F7: The same function is covered under COPNI Group 01.0.
F9: This group corresponds to Group 04.1 (individual consumption expenditure of households on actual rentals for housing) and Group 15.1 (individual consumption expenditure of general government on housing).
B11: 14.1.0 | C11: 14.1.0.0 | D11: 14.1.0.00 | E11: 14.1.0.000 | F11: Housing (S) | G11: 14.1.0.0 | H11: 13.1.000 | I11: 72111
F13: As specified in COPNI 01.0.0. Corresponds to (04.1.1) and (15.1.0).
A15: 14.2 | F15: HEALTH
F17: The same function is covered under COPNI Groups 02.1 to 02.6.
F19: This group corresponds to Division 06 (individual consumption expenditure of households on health) and Group 15.2 (individual consumption expenditure of general government on health).
B21: 14.2.1 | C21: 14.2.1.0 | D21: 14.2.1.00 | E21: 14.2.1.000 | F21: Pharmaceutical products (ND) | G21: 14.2.1.0 | H21: 13.2.100 | I21: 35260; 35270; 35290
F23: As specified in COPNI 02.1.1. Corresponds to (06.1.1) and (15.2.1).
B25: 14.2.2 | C25: 14.2.2.0 | D25: 14.2.2.00 | E25: 14.2.2.000 | F25: Other medical products (ND) | G25: 14.2.2.0 | H25: 13.2.200 | I25: 35270; 35290
F27: As specified in COPNI 02.1.2. Corresponds to (06.1.2) and (15.2.2).
B29: 14.2.3 | C29: 14.2.3.0 | D29: 14.2.3.00 | E29: 14.2.3.000 | F29: Therapeutic appliances and equipment (D) | G29: 14.2.3.0 | H29: 13.2.300 | I29: 48110; 48121; 48122; 48130; 48140; 48150; 48160; 48171; 48172; 48180
F31: As specified in COPNI 02.1.3. Corresponds to (06.1.3) and (15.2.3).
B33: 14.2.4 | C33: 14.2.4.0 | D33: 14.2.4.00 | E33: 14.2.4.000 | F33: Outpatient medical services (S) | G33: 14.2.4.0 | H33: 13.2.400 | I33: 93121; 93122
F35: As specified in COPNI 02.2.1. Corresponds to (06.2.1), (06.2.3), and (15.2.4).
B37: 14.2.5 | C37: 14.2.5.0 | D37: 14.2.5.00 | E37: 14.2.5.000 | F37: Outpatient dental services (S) | G37: 14.2.5.0 | H37: 13.2.500 | I37: 93123
F39: As specified in COPNI 02.2.2. Corresponds to (06.2.2) and (15.2.5).
B41: 14.2.6 | C41: 14.2.6.0 | D41: 14.2.6.00 | E41: 14.2.6.000 | F41: Outpatient paramedical services (S) | G41: 14.2.6.0 | H41: 13.2.600 | I41: 93191; 93192; 93193
F43: As specified in COPNI 02.2.3. Corresponds to (06.4) and (15.2.6).
B45: 14.2.7 | C45: 14.2.7.0 | D45: 14.2.7.00 | E45: 14.2.7.000 | F45: Hospital services (S) | G45: 14.2.7.0 | H45: 13.2.700 | I45: 93111; 93112; 93113; 93119
F47: As specified in COPNI 02.3.0. Corresponds to (06.3) and (15.2.7).
B49: 14.2.8 | C49: 14.2.8.0 | D49: 14.2.8.00 | E49: 14.2.8.000 | F49: Other health services (S) | G49: 14.2.8.0 | H49: 13.2.800 | I49: 93194; 93195; 93196; 93197; 93199
F51: As specified in COPNI 02.4.0, 02.5.0 and 02.6.0.
A53: 14.3 | F53: RECREATION AND CULTURE
F55: The same function is covered under COPNI Groups 03.1 and 03.2.
F57: This group corresponds to Groups 09.4 and 09.6 (individual consumption expenditure of households on recreational and cultural services) and Group 15.3 (individual consumption expenditure of general government on recreation and culture).
B59: 14.3.1 | C59: 14.3.1.0 | D59: 14.3.1.00 | E59: 14.3.1.000 | F59: Recreational and sporting services (S) | G59: 14.3.1.0 | H59: 13.3.100 | I59: 96p
F61: 14.3.1 Recreational and sporting services (S) As specified in COPNI 03.1.0. Corresponds to (09.4) and (15.3.1).
B63: 14.3.2 | C63: 14.3.2.0 | D63: 14.3.2.00 | E63: 14.3.2.000 | F63: Cultural services (S) | G63: 14.3.2.0 | H63: 13.3.200 | I63: 96p
F65: As specified in COPNI 03.2.0. Corresponds to (09.6) and (15.3.2).
A67: 14.4 | F67: EDUCATION
F69: The same function is covered under COPNI Groups 04.1 to 04.7.
F71: This group corresponds to Division 10 (individual consumption expenditure of households on education) and Group 15.4 (individual consumption expenditure of general government on education).
B73: 14.4.1 | C73: 14.4.1.0 | D73: 14.4.1.00 | E73: 14.4.1.000 | F73: Pre-primary and primary education (S) | G73: 14.4.1.0 | H73: 13.4.100 | I73: 92100; 92200
F75: As specified in COPNI 04.1.0. Corresponds to (10.1.0) and (15.4.1).
B77: 14.4.2 | C77: 14.4.2.0 | D77: 14.4.2.00 | E77: 14.4.2.000 | F77: Secondary education (S) | G77: 14.4.2.0 | H77: 13.4.200 | I77: 92310
F79: As specified in COPNI 04.2.0. Corresponds to (10.2.0) and (15.4.2).
B81: 14.4.3 | C81: 14.4.3.0 | D81: 14.4.3.00 | E81: 14.4.3.000 | F81: Post-secondary non-tertiary education (S) | G81: 14.4.3.0 | H81: 13.4.300 | I81: 92410; 92420
F83: As specified in COPNI 04.3.0. Corresponds to (10.3.0) and (15.4.3).
B85: 14.4.4 | C85: 14.4.4.0 | D85: 14.4.4.00 | E85: 14.4.4.000 | F85: Tertiary education (S) | G85: 14.4.4.0 | H85: 13.4.400 | I85: 92510; 92520
F87: As specified in COPNI 04.4.0. Corresponds to (10.4.0) and (15.4.4).
B89: 14.4.5 | C89: 14.4.5.0 | D89: 14.4.5.00 | E89: 14.4.5.000 | F89: Education not definable by level (S) | G89: 14.4.5.0 | H89: 13.4.500 | I89: 92911; 92919; 92920
F91: As specified in COPNI 04.5.0. Corresponds to (10.5.0) and (15.4.5).
B93: 14.4.6 | C93: 14.4.6.0 | D93: 14.4.6.00 | E93: 14.4.6.000 | F93: Other educational services (S) | G93: 14.4.6.0 | H93: 13.4.600 | I93: 92911; 92919; 92920
F95: As specified in COPNI 04.6.0 and 04.7.0.
A97: 14.5 | F97: SOCIAL PROTECTION
F99: The same function is covered under COPNI Groups 05.1 and 05.2.
F101: This group corresponds to Group 13.3 (individual consumption expenditure of households on social protection) and Group 15.5 (individual consumption expenditure of general government on social protection).
B103: 14.5.0 | C103: 14.5.0.0 | D103: 14.5.0.00 | E103: 14.5.0.000 | F103: Social protection (S) | G103: 14.5.0.0 | H103: 13.5.000 | I103: 93221; 93222; 93223; 93301; 93302; 93303; 93304
F105: As specified in COPNI 05.1.0 and 05.2.0. Corresponds to (13.3.0) and (15.5.0).
A107: 14.6 | F107: OTHER SERVICES
F109: These functions are covered under COPNI Groups 06.0, 07.1, 07.2, 07.3, 08.1, 08.2, 09.1 and 09.2.
F111: This group has to great extend no counterpart in Divisions 01 to 13 (individual consumption expenditure of households) or in Division 15 (individual consumption expenditure of general government). The only exception is religion which correspond to Subclass 13.9.0.2 Religious services.
B113: 14.6.1 | C113: 14.6.1.0 | D113: 14.6.1.00 | E113: 14.6.1.000 | F113: Religion (S) | G113: 14.6.1.0 | H113: 13.6.100 | I113: 95910
F115: As specified in COPNI 06.0.0. Corresponds to (13.9.0.2).
B117: 14.6.2 | C117: 14.6.2.0 | D117: 14.6.2.00 | E117: 14.6.2.000 | F117: Political parties, labour and professional organizations (S) | G117: 14.6.2.0 | H117: 13.6.200 | I117: 95p
F119: As specified in COPNI 07.1.0, 07.2.0 and 07.3.0.
B121: 14.6.3 | C121: 14.6.3.0 | D121: 14.6.3.00 | E121: 14.6.3.000 | F121: Environmental protection (S) | G121: 14.6.3.0 | H121: 13.6.300 | I121: 94p
F123: As specified in COPNI 08.1.0 and 08.2.0.
B125: 14.6.4 | C125: 14.6.4.0 | D125: 14.6.4.00 | E125: 14.6.4.000 | F125: Services n.e.c. (S) | G125: 14.6.4.0 | H125: 13.6.400 | I125: 97p
F127: As specified in COPNI 09.1.0 and 09.2.0.

Sheet Division 15
A1: Group | B1: Class | C1: Sub-Class | D1: Item | E1: Sub-Item | F1: Description | G1: 2018 UN COICOP | H1: 2009 PCOICOP | I1: CPC 2.1
F3: DIVISION 15: INDIVIDUAL CONSUMPTION EXPENDITURE OF GENERAL GOVERNMENT
A5: 15.1 | F5: HOUSING
F7: The same function is covered under COFOG Group 10.6.
F9: This group corresponds to Group 04.1 (individual consumption expenditure of households on actual rentals for housing) and Group 14.1 (individual consumption expenditure of NPISHs on housing).
B11: 15.1.0 | C11: 15.1.0.0 | D11: 15.1.0.00 | E11: 15.1.0.000 | F11: Housing (S) | G11: 15.1.0.0 | H11: 14.1.000 | I11: 7211
F13: As specified in COFOG 10.6.0. Corresponds to (04.1.1) and (14.1.0).
A15: 15.2 | F15: HEALTH
F17: The same function is covered under COFOG Groups 07.1 to 07.4.
F19: This group corresponds to Division 06 (individual consumption expenditure of households on health) and Group 14.2 (individual consumption expenditure of NPISHs on health).
B21: 15.2.1 | C21: 15.2.1.0 | D21: 15.2.1.00 | E21: 15.2.1.000 | F21: Pharmaceutical products (ND) | G21: 15.2.1.0 | H21: 14.2.100 | I21: 35260 35290
F23: As specified in COFOG 07.1.1. Corresponds to (06.1.1) and (14.2.1).
B25: 15.2.2 | C25: 15.2.2.0 | D25: 15.2.2.00 | E25: 15.2.2.000 | F25: Other medical products (ND) | G25: 15.2.2.0 | H25: 14.2.200 | I25: 35290
F27: As specified in COFOG 07.1.2. Corresponds to (06.1.2) and (14.2.2).
B29: 15.2.3 | C29: 15.2.3.0 | D29: 15.2.3.00 | E29: 15.2.3.000 | F29: Therapeutic appliances and equipment (D) | G29: 15.2.3.0 | H29: 14.2.300 | I29: 4481
F31: As specified in COFOG 07.1.3. Corresponds to (06.1.3) and (14.2.3).
B33: 15.2.4 | C33: 15.2.4.0 | D33: 15.2.4.00 | E33: 15.2.4.000 | F33: Outpatient medical services (S) | G33: 15.2.4.0 | H33: 14.2.400 | I33: 93121 93122
F35: As specified in COFOG 07.2.1 and 07.2.2. Corresponds to (06.2.1), (06.2.3), and (14.2.4).
B37: 15.2.5 | C37: 15.2.5.0 | D37: 15.2.5.00 | E37: 15.2.5.000 | F37: Outpatient dental services (S) | G37: 15.2.5.0 | H37: 14.2.500 | I37: 93123
F39: As specified in COFOG 07.2.3. Corresponds to (06.2.2) and (14.2.5).
B41: 15.2.6 | C41: 15.2.6.0 | D41: 15.2.6.00 | E41: 15.2.6.000 | F41: Outpatient paramedical services (S) | G41: 15.2.6.0 | H41: 14.2.600 | I41: 93191 93192 93193
F43: As specified in COFOG 07.2.4. Corresponds to (06.2.1), (06.2.3), (06.4.1), and (14.2.6).
B45: 15.2.7 | C45: 15.2.7.0 | D45: 15.2.7.00 | E45: 15.2.7.000 | F45: Hospital services (S) | G45: 15.2.7.0 | H45: 14.2.700 | I45: 9311
F47: As specified in COFOG 07.3.1, 07.3.2, 07.3.3 and 07.3.4. Corresponds to (06.3) and (14.2.6).
B49: 15.2.8 | C49: 15.2.8.0 | D49: 15.2.8.00 | E49: 15.2.8.000 | F49: Public health services (S) | G49: 15.2.8.0 | H49: 14.2.800 | I49: 93199
F51: As specified in COFOG 07.4.0.
A53: 15.3 | F53: RECREATION AND CULTURE
F55: The same function is covered under COFOG Groups 08.1 and 08.2.
F57: This group corresponds to Groups 09.4 and 09.6 (individual consumption expenditure of households on recreational and cultural services) and Group 14.3 (individual consumption expenditure of NPISHs on recreation and culture).
B59: 15.3.1 | C59: 15.3.1.0 | D59: 15.3.1.00 | E59: 15.3.1.000 | F59: Recreational and sporting services (S) | G59: 15.3.1.0 | H59: 14.3.100 | I59: 96 p
F61: As specified in COFOG 08.1.0. Corresponds to (09.4) and (14.3.1).
B63: 15.3.2 | C63: 15.3.2.0 | D63: 15.3.2.00 | E63: 15.3.2.000 | F63: Cultural services (S) | G63: 15.3.2.0 | H63: 14.3.200 | I63: 96 p
F65: As specified in COFOG 08.2.0. Corresponds to (09.6) and (14.3.2).
A67: 15.4 | F67: EDUCATION
F69: The same function is covered under COFOG Groups 09.1 to 09.6.
F71: This group corresponds to Division 10 (individual consumption expenditure of households on education), Group 14.4 (individual consumption expenditure of NPISHs on education).
B73: 15.4.1 | C73: 15.4.1.0 | D73: 15.4.1.00 | E73: 15.4.1.000 | F73: Pre-primary and primary education (S) | G73: 15.4.1.0 | H73: 14.4.100 | I73: 92100 92200
F75: As specified in COFOG 09.1.1 and 09.1.2. Corresponds to (10.1.0) and (14.4.1).
B77: 15.4.2 | C77: 15.4.2.0 | D77: 15.4.2.00 | E77: 15.4.2.000 | F77: Secondary education (S) | G77: 15.4.2.0 | H77: 14.4.200 | I77: 923
F79: As specified in COFOG 09.2.1 and 09.2.2. Corresponds to (10.2.0) and (14.4.2).
B81: 15.4.3 | C81: 15.4.3.0 | D81: 15.4.3.00 | E81: 15.4.3.000 | F81: Post-secondary non-tertiary education (S) | G81: 15.4.3.0 | H81: 14.4.300 | I81: 924
F83: As specified in COFOG 09.3.0. Corresponds to (10.3.0) and (14.4.3).
B85: 15.4.4 | C85: 15.4.4.0 | D85: 15.4.4.00 | E85: 15.4.4.000 | F85: Tertiary education (S) | G85: 15.4.4.0 | H85: 14.4.400 | I85: 925
F87: As specified in COFOG 09.4.1 and 09.4.2. Corresponds to (10.4.0) and (14.4.4).
B89: 15.4.5 | C89: 15.4.5.0 | D89: 15.4.5.00 | E89: 15.4.5.000 | F89: Education not definable by level (S) | G89: 15.4.5.0 | H89: 14.4.500 | I89: 929
F91: As specified in COFOG 09.5.0. Corresponds to (10.5.0) and (14.4.5).
B93: 15.4.6 | C93: 15.4.6.0 | D93: 15.4.6.00 | E93: 15.4.6.000 | F93: Subsidiary services to education (S) | G93: 15.4.6.0 | H93: 14.4.600 | I93: 929
F95: As specified in COFOG 09.6.0.
A97: 15.5 | F97: SOCIAL PROTECTION
F99: The same function is covered under COFOG Groups 10.1 to 10.5 and Group 10.7.
F101: This group corresponds to Group 13.3 (individual consumption expenditure of households on social protection) and Group 14.5 (individual consumption expenditure of NPISHs on social protection).
B103: 15.5.0 | C103: 15.5.0.0 | D103: 15.5.0.00 | E103: 15.5.0.000 | F103: Social protection (S) | G103: 15.5.0.0 | H103: 14.5.000 | I103: 933
F105: As specified in COFOG 10.1.1 to 10.5.0 and 10.7.0. Corresponds to (13.3.0) and (14.5.0).

Sheet CPC
A1: CPC2.1 | B1: CPC2 | C1: CPC1.1 | D1: UNCOICOP 1999 | E1: CPC21title | F1: 1to1 | G1: 1 to many
A2: 01111 | B2: 01111 | C2: 01110 | D2: 01.1.1 | E2: Wheat, seed | F2: 1
A3: 01112 | B3: 01112 | C3: 01110 | D3: 01.1.1 | E3: Wheat, other | F3: 1
A4: 01121 | B4: 01121 | C4: 01120 | D4: 01.1.1 | E4: Maize (corn), seed | F4: 1
A5: 01122 | B5: 01122 | C5: 01120 | D5: 01.1.1 | E5: Maize (corn), other | F5: 1
A6: 01131 | B6: 01131 | C6: 01130 | D6: 01.1.1 | E6: Rice, seed | F6: 1
A7: 01132 | B7: 01132 | C7: 01130 | D7: 01.1.1 | E7: Rice paddy, other (not husked) | F7: 1
A8: 23162 | B8: 23162 | C8: 01140 | D8: 01.1.1 | E8: Husked rice | F8: 1
A9: 01151 | B9: 01151 | C9: 01150 | D9: 01.1.1 | E9: Barley, seed | F9: 1
A10: 01152 | B10: 01152 | C10: 01150 | D10: 01.1.1 | E10: Barley, other | F10: 1
A11: 01161 | B11: 01161 | C11: 01160 | D11: 01.1.1 | E11: Rye, seed | F11: 1
A12: 01162 | B12: 01162 | C12: 01160 | D12: 01.1.1 | E12: Rye, other | F12: 1
A13: 01171 | B13: 01171 | C13: 01160 | D13: 01.1.1 | E13: Oats, seed | F13: 1
... A352: 03219 | B352: 03219 | C352: 03230 | D352: 02.3.0 | E352: Lac, resins, balsams, natural gums and other resins n.e.c. | F352: 1
A353: 35250 | B353: 35250 | C353: 35250 | D353: 02.3.0 | E353: Provitamins, vitamins and hormones; glycosides and vegetable alkaloids and their salts, ethers, esters and other derivatives; antibiotics | F353: 1
A354: 26510 | B354: 26510 | C354: 26510 | D354: 03.1.1 | E354: Woven fabrics of silk or of silk waste | F354: 1
A355: 26520 | B355: 26520 | C355: 26520 | D355: 03.1.1 | E355: Woven fabrics of carded wool or of carded fine animal hair, containing 85% or more by weight of wool or fine animal hair | F355: 1
A356: 26530 | B356: 26530 | C356: 26530 | D356: 03.1.1 | E356: Woven fabrics of combed wool or of combed fine animal hair, containing 85% or more by weight of wool or fine animal hair | F356: 1
A357: 26540 | B357: 26540 | C357: 26540 | D357: 03.1.1 | E357: Woven fabrics of wool or fine animal hair, containing less than 85% by weight of wool or fine animal hair | F357: 1
A358: 26550 | B358: 26550 | C358: 26550 | D358: 03.1.1 | E358: Woven fabrics of coarse animal hair or of horsehair | F358: 1
A359: 26560 | B359: 26560 | C359: 26560 | D359: 03.1.1 | E359: Woven fabrics of flax | F359: 1
A360: 26570 | B360: 26570 | C360: 26570 | D360: 03.1.1 | E360: Woven fabrics of jute and other textile bast fibres (except flax, true hemp and ramie) | F360: 1
A361: 26590 | B361: 26590 | C361: 26590 | D361: 03.1.1 | E361: Woven fabrics of other vegetable textile fibres; woven fabrics of paper yarn | F361: 1
A362: 26610 | B362: 26610 | C362: 26610 | D362: 03.1.1 | E362: Woven fabrics of cotton, containing 85% or more by weight of cotton, weighing not more than 200 g/m2 | F362: 1
A363: 26620 | B363: 26620 | C363: 26620 | D363: 03.1.1 | E363: Woven fabrics of cotton, containing 85% or more by weight of cotton, weighing more than 200 g/m2 | F363: 1
A364: 26630 | B364: 26630 | C364: 26630 | D364: 03.1.1 | E364: Woven fabrics of cotton, containing less than 85% by weight of cotton, mixed mainly or solely with man-made fibres | F364: 1
A365: 26690 | B365: 26690 | C365: 26690 | D365: 03.1.1 | E365: Other woven fabrics of cotton | F365: 1
... A936: 99000 | B936: 99000 | C936: 99000 | D936: 12.7.0 | E936: Services provided by extraterritorial organizations and bodies | F936: 1
A937: 01356 | B937: 01391 | C937: 01231 | E937: Locust beans (carobs)
A938: 01211 | B938: 01211 | C938: 01239 | E938: Asparagus | G938: 2
A939: 01212 | B939: 01212 | C939: 01239 | E939: Cabbages | G939: 2
A940: 01213 | B940: 01213 | C940: 01239 | E940: Cauliflowers and broccoli | G940: 2
A941: 01214 | B941: 01214 | C941: 01239 | E941: Lettuce and chicory | G941: 2
A942: 01215 | B942: 01215 | C942: 01239 | E942: Spinach | G942: 2
A943: 01216 | B943: 01216 | C943: 01239 | E943: Artichokes | G943: 2
A944: 01219 | B944: 01219 | C944: 01239 | E944: Other leafy or stem vegetables | G944: 2
A945: 01231 | B945: 01231 | C945: 01239 | E945: Chillies and peppers, green (<i>Capsicum</i> spp. and <i>Pimenta</i> spp.) | G945: 2
A946: 01232 | B946: 01232 | C946: 01239 | E946: Cucumbers and gherkins | G946: 2
A947: 01233 | B947: 01233 | C947: 01239 | E947: Eggplants (aubergines) | G947: 2
A948: 01234 | B948: 01234 | C948: 01239 | E948: Tomatoes | G948: 2
A949: 01235 | B949: 01235 | C949: 01239 | E949: Pumpkins, squash and gourds | G949: 2
... A962: 01450 | B962: 01450 | C962: 01239 | E962: Olives | G962: 2
A963: 01411 | B963: 01411 | C963: 01410 | E963: Soya beans, seed for planting
A964: 01412 | B964: 01412 | C964: 01410 | E964: Soya beans, other
A965: 01431 | B965: 01431 | C965: 01440 | E965: Cottonseed, seed for planting
A966: 01432 | B966: 01432 | C966: 01440 | E966: Cottonseed, other
A967: 01260 | B967: 01260 | C967: 01540 | E967: Vegetable seeds, except beet seeds
A968: 01640 | B968: 01640 | C968: 01614 | E968: Cocoa beans
A969: 25010 | B969: 25010 | C969: 01710 | E969: Cured stemmed/stripped tobacco leaves
A970: 01970 | B970: 01970 | C970: 01790 | E970: Unmanufactured tobacco
A971: 01801 | B971: 01801 | C971: 01810 | E971: Sugar beet
A972: 01911 | B972: 01911 | C972: 01910 | E972: Maize for forage and silage
A973: 01912 | B973: 01912 | C973: 01910 | E973: Alfalfa for forage and silage
A974: 01913 | B974: 01913 | C974: 01910 | E974: Cereal straw, husks, unprepared, ground, pressed, or in the form of pellets
... A979: 01809 | B979: 01809 | C979: 01990 | E979: Other sugar crops n.e.c.
A980: 02111 | B980: 02111 | C980: 02111 | E980: Cattle | G980: 2
A981: 02112 | B981: 02112 | C981: 02111 | E981: Buffalo | G981: 2
A982: 02131 | B982: 02130 | C982: 02113 | E982: Horses | G982: 3
A983: 02132 | B983: 02130 | C983: 02113 | E983: Asses | G983: 3
A984: 02133 | B984: 02130 | C984: 02113 | E984: Mules and hinnies | G984: 3
A985: 02121 | B985: 02121 | C985: 02129 | E985: Camels and camelids | G985: 3
A986: 02129 | B986: 02129 | C986: 02129 | E986: Other ruminants, n.e.c. | G986: 3
A987: 02191 | B987: 02191 | C987: 02129 | E987: Rabbits and hares | G987: 3
A988: 02192 | B988: 02192 | C988: 02129 | E988: Other mammals | G988: 3
A989: 02193 | B989: 02193 | C989: 02129 | E989: Ostriches and emus | G989: 3
A990: 02194 | B990: 02194 | C990: 02129 | E990: Other birds | G990: 3
A991: 02195 | B991: 02195 | C991: 02129 | E991: Reptiles | G991: 3
... A994: 02930 | B994: 02930 | C994: 02950 | E994: Edible products of animal origin n.e.c. | G994: 2
A995: 02941 | B995: 02941 | C995: 02961 | E995: Shorn wool, greasy, including fleece-washed shorn wool
A996: 02942 | B996: 02942 | C996: 02962 | E996: Pulled wool, greasy, including fleece-washed pulled wool; coarse animal hair
A997: 02943 | B997: 02943 | C997: 02963 | E997: Fine animal hair, not carded or combed
A998: 02944 | B998: 02944 | C998: 02964 | E998: Silk-worm cocoons suitable for reeling
A999: 02951 | B999: 02951 | C999: 02971 | E999: Raw hides and skins of bovine animals
A1000: 02952 | B1000: 02952 | C1000: 02971 | E1000: Raw hides and skins of equine animals
A1001: 02953 | B1001: 02953 | C1001: 02971 | E1001: Raw hides and skins of sheep or lambs
A1002: 02954 | B1002: 02954 | C1002: 02971 | E1002: Raw hides and skins of goats or kids
A1003: 02960 | B1003: 02960 | C1003: 02980 | E1003: Insect waxes and spermaceti, whether or not refined or coloured
A1004: 02411 | B1004: 02411 | C1004: 02990 | E1004: Bovine semen
A1005: 03110 | B1005: 03110 | C1005: 03110 | E1005: Logs of coniferous wood
A1006: 03120 | B1006: 03120 | C1006: 03120 | E1006: Logs of non-coniferous wood
... A1010: 03250 | B1010: 03250 | C1010: 03930 | E1010: Vegetable materials of a kind used primarily for plaiting or as stuffing or padding; raw vegetable materials of a kind used primarily for dyeing or tanning; vegetable products n.e.c.
A1011: 04111 | B1011: 04111 | C1011: 04110 | E1011: Wild ornamental fish | G1011: 2
A1012: 04112 | B1012: 04111 | C1012: 04110 | E1012: Farmed ornamental fish | G1012: 2
A1013: 04191 | B1013: 04119 | C1013: 04110 | E1013: Other wild live fish, not for human consumption, including seeds and feeds for aquaculture | G1013: 2
A1014: 04192 | B1014: 04119 | C1014: 04110 | E1014: Other farmed live fish, not for human consumption, including seeds and feeds for aquaculture | G1014: 2
A1015: 11050 | B1015: 11050 | C1015: 11040 | E1015: Peat | G1015: 2
A1016: 12010 | B1016: 12010 | C1016: 12010 | E1016: Petroleum oils and oils obtained from bituminous minerals, crude
A1017: 12020 | B1017: 12020 | C1017: 12020 | E1017: Natural gas, liquefied or in the gaseous state
A1018: 12030 | B1018: 12030 | C1018: 12030 | E1018: Bituminous or oil shale and tar sands
A1019: 13000 | B1019: 13000 | C1019: 13000 | E1019: Uranium and thorium ores and concentrates
A1020: 14100 | B1020: 14100 | C1020: 14100 | E1020: Iron ores and concentrates, other than roasted iron pyrites
A1021: 14210 | B1021: 14210 | C1021: 14210 | E1021: Copper, ores and concentrates
A1022: 14220 | B1022: 14220 | C1022: 14220 | E1022: Nickel ores and concentrates
A1023: 14230 | B1023: 14230 | C1023: 14230 | E1023: Aluminium ores and concentrates
A1024: 14240 | B1024: 14240 | C1024: 14240 | E1024: Precious metal ores and concentrates
A1025: 14290 | B1025: 14290 | C1025: 14290 | E1025: Other non-ferrous metal ores and concentrates (other than uranium or thorium ores and concentrates)
A1026: 15110 | B1026: 15110 | C1026: 15110 | E1026: Slate
A1027: 15120 | B1027: 15120 | C1027: 15120 | E1027: Marble and other calcareous monumental or building stone
... A1040: 21330 | B1040: 21330 | C1040: 21320 | E1040: Vegetables provisionally preserved
A1041: 21340 | B1041: 21340 | C1041: 21390 | E1041: Vegetables, pulses and potatoes, preserved by vinegar or acetic acid | G1041: 3
...

Sheet PCOICOP Test
A1: 2009 PCOICOP | B1: Description | C1: 2009 Concordance | E1: 2009 PCOICOP | F1: Description | G1: 2009 Concordance | I1: 2009 PCOICOP | J1: Description
A2: 01.1.111 | B2: Well milled premium rice, fragrant, polished, or glazed, e.g. Jasmine, Sinandomeng, Dinorado, Milagrosa, Wagwag, Glutinous rice etc. | C2: =VLOOKUP(A2,'Completeness(1)'!$A$1:$A$294,1,FALSE) -> 01.1.111 | E2: 04.1.110 | F2: Actual rentals paid by tenants or subtenants occupying unfurnished premises as their main residence | G2: =VLOOKUP(E2,'Completeness(4)'!$A$1:$A$55,1,FALSE) -> 04.1.110 | I2: 06.1.111 | J2: Infections and infestations | K2: =VLOOKUP(I2,'Completeness(6)'!$A$1:$A$25,1,FALSE) -> 06.1.111
A3: 01.1.112 | B3: Brown Rice | C3: =VLOOKUP(A3,'Completeness(1)'!$A$1:$A$294,1,FALSE) -> 01.1.112 | E3: 04.1.120 | F3: Actual rentals paid by tenants or subtenants occupying furnished premises as their main residence | G3: =VLOOKUP(E3,'Completeness(4)'!$A$1:$A$55,1,FALSE) -> 04.1.120 | I3: 06.1.112 | J3: Hypertensive and cardiovascular diseases | K3: =VLOOKUP(I3,'Completeness(6)'!$A$1:$A$25,1,FALSE) -> 06.1.112
A4: 01.1.113 | B4: Regular milled, commercial rice, unpolished, unglazed, except NFA rice | C4: =VLOOKUP(A4,'Completeness(1)'!$A$1:$A$294,1,FALSE) -> 01.1.113 | E4: 04.1.130 | F4: Payment by households occupying a room in a hotel or boarding house as their main residence | G4: =VLOOKUP(E4,'Completeness(4)'!$A$1:$A$55,1,FALSE) -> 04.1.130 | I4: 06.1.113 | J4: Pain relief and consciousness such as analgesic, immunology such as anesthetics, and immunosuppresants | K4: =VLOOKUP(I4,'Completeness(6)'!$A$1:$A$25,1,FALSE) -> 06.1.113
A5: 01.1.114 | B5: NFA Rice | C5: =VLOOKUP(A5,'Completeness(1)'!$A$1:$A$294,1,FALSE) -> 01.1.114 | E5: 04.1.140 | F5: Parking lot payments in connection with the dwelling as main residence | G5: =VLOOKUP(E5,'Completeness(4)'!$A$1:$A$55,1,FALSE) -> 04.1.140 | I5: 06.1.114 | J5: Allergy and respiratory diseases | K5: =VLOOKUP(I5,'Completeness(6)'!$A$1:$A$25,1,FALSE) -> 06.1.114
A6: 01.1.115 | B6: Overmilled, broken rice | C6: =VLOOKUP(A6,'Completeness(1)'!$A$1:$A$294,1,FALSE) -> 01.1.115 | E6: 04.1.190 | F6: Other actual rental paid in other types of main residence | G6: =VLOOKUP(E6,'Completeness(4)'!$A$1:$A$55,1,FALSE) -> 04.1.190 | I6: 06.1.115 | J6: Endocrine and central nervous system | K6: =VLOOKUP(I6,'Completeness(6)'!$A$1:$A$25,1,FALSE) -> 06.1.115
A7: 01.1.119 | B7: Other rice, n.e.c | C7: =VLOOKUP(A7,'Completeness(1)'!$A$1:$A$294,1,FALSE) -> 01.1.119 | E7: 04.1.200 | F7: Other actual rentals (S) | G7: =VLOOKUP(E7,'Completeness(4)'!$A$1:$A$55,1,FALSE) -> 04.1.200 | I7: 06.1.121 | J7: Serums and vaccines | K7: =VLOOKUP(I7,'Completeness(6)'!$A$1:$A$25,1,FALSE) -> #N/A
A8: 01.1.121 | B8: Corn, on the cob, yellow | C8: =VLOOKUP(A8,'Completeness(1)'!$A$1:$A$294,1,FALSE) -> 01.1.121 | E8: 04.2.110 | F8: Own or owner-like possession of house and lot | G8: =VLOOKUP(E8,'Completeness(4)'!$A$1:$A$55,1,FALSE) -> 04.2.110 | I8: 06.1.122 | J8: Vitamins and minerals | K8: =VLOOKUP(I8,'Completeness(6)'!$A$1:$A$25,1,FALSE) -> 06.1.122
A9: 01.1.122 | B9: Corn on the cob, white | C9: =VLOOKUP(A9,'Completeness(1)'!$A$1:$A$294,1,FALSE) -> 01.1.122 | E9: 04.2.120 | F9: Rent house/room including lot | G9: =VLOOKUP(E9,'Completeness(4)'!$A$1:$A$55,1,FALSE) -> #N/A | I9: 06.1.123 | J9: Cod liver oil and halibut liver oil | K9: =VLOOKUP(I9,'Completeness(6)'!$A$1:$A$25,1,FALSE) -> #N/A
A10: 01.1.123 | B10: Whole corn, grain | C10: =VLOOKUP(A10,'Completeness(1)'!$A$1:$A$294,1,FALSE) -> 01.1.123 | E10: 04.2.210 | F10: Imputed rentals for secondary residence | G10: =VLOOKUP(E10,'Completeness(4)'!$A$1:$A$55,1,FALSE) -> 04.2.210 | I10: 06.1.124 | J10: Dietary supplements | K10: =VLOOKUP(I10,'Completeness(6)'!$A$1:$A$25,1,FALSE) -> #N/A
A11: 01.1.124 | B11: Glutinous corn, | C11: =VLOOKUP(A11,'Completeness(1)'!$A$1:$A$294,1,FALSE) -> 01.1.124 | E11: 04.2.220 | F11: Imputed rentals of households paying a reduced rental or housed free. | G11: =VLOOKUP(E11,'Completeness(4)'!$A$1:$A$55,1,FALSE) -> 04.2.220 | I11: 06.1.129 | J11: Other pharmaceutical products or articles for medical or surgical purposes disinfectant | K11: =VLOOKUP(I11,'Completeness(6)'!$A$1:$A$25,1,FALSE) -> 06.1.129
A12: 01.1.125 | B12: Popcorn (variety) | C12: =VLOOKUP(A12,'Completeness(1)'!$A$1:$A$294,1,FALSE) -> 01.1.125 | E12: 04.3.110 | F12: Paints and varnishes | G12: =VLOOKUP(E12,'Completeness(4)'!$A$1:$A$55,1,FALSE) -> 04.3.110 | I12: 06.1.191 | J12: Local herbal medicines | K12: =VLOOKUP(I12,'Completeness(6)'!$A$1:$A$25,1,FALSE) -> 06.1.191
A13: 01.1.126 | B13: Corn grits, milled | C13: =VLOOKUP(A13,'Completeness(1)'!$A$1:$A$294,1,FALSE) -> 01.1.126 | E13: 04.3.120 | F13: Wallpaper, wall paper pastes and fabric wall covering | G13: =VLOOKUP(E13,'Completeness(4)'!$A$1:$A$55,1,FALSE) -> 04.3.120 | I13: 06.1.192 | J13: Dermatology | K13: =VLOOKUP(I13,'Completeness(6)'!$A$1:$A$25,1,FALSE) -> #N/A
... A42: 01.1.211 | B42: Meat of bovine animals, (cattle, buffallo, carabao) | C42: =VLOOKUP(A42,'Completeness(1)'!$A$1:$A$294,1,FALSE) -> 01.1.211 | E42: 04.5.410 | F42: Fuel wood, in logs, in billets, in twigs, in faggots or in similar forms | G42: =VLOOKUP(E42,'Completeness(4)'!$A$1:$A$55,1,FALSE) -> 04.5.410 | I42: 06.3.020 | J42: Private hospital services | K42: =VLOOKUP(I42,'Completeness(6)'!$A$1:$A$25,1,FALSE) -> #N/A
A43: 01.1.212 | B43: Meat of swine | C43: =VLOOKUP(A43,'Completeness(1)'!$A$1:$A$294,1,FALSE) -> 01.1.212 | E43: 04.5.420 | F43: Coal, not agglomerated, briquettes and similar solid fuels, coke and semi-coke of coal, of lignite or of peat, retort carbon manufactured from coal | G43: =VLOOKUP(E43,'Completeness(4)'!$A$1:$A$55,1,FALSE) -> 04.5.420
A44: 01.1.213 | B44: Meat of sheep | C44: =VLOOKUP(A44,'Completeness(1)'!$A$1:$A$294,1,FALSE) -> 01.1.213 | E44: 04.5.430 | F44: Lignite, whether or not agglomerated | G44: =VLOOKUP(E44,'Completeness(4)'!$A$1:$A$55,1,FALSE) -> #N/A
A45: 01.1.214 | B45: Meat of goats | C45: =VLOOKUP(A45,'Completeness(1)'!$A$1:$A$294,1,FALSE) -> 01.1.214 | E45: 04.5.440 | F45: Wood charcoal | G45: =VLOOKUP(E45,'Completeness(4)'!$A$1:$A$55,1,FALSE) -> 04.5.440
A46: 01.1.215 | B46: Meat of horses | C46: =VLOOKUP(A46,'Completeness(1)'!$A$1:$A$294,1,FALSE) -> #N/A | E46: 04.5.450 | F46: Sawdust and wood waste and scrap | G46: =VLOOKUP(E46,'Completeness(4)'!$A$1:$A$55,1,FALSE) -> 04.5.450
A47: 01.1.216 | B47: Meat of chicken | C47: =VLOOKUP(A47,'Completeness(1)'!$A$1:$A$294,1,FALSE) -> 01.1.216 | E47: 04.5.490 | F47: Other solid fuels, n.e.c | G47: =VLOOKUP(E47,'Completeness(4)'!$A$1:$A$55,1,FALSE) -> 04.5.490
A48: 01.1.217 | B48: Meat of turkey | C48: =VLOOKUP(A48,'Completeness(1)'!$A$1:$A$294,1,FALSE) -> 01.1.217 | E48: 04.5.510 | F48: Hot water and steam purchased from district heating plants | G48: =VLOOKUP(E48,'Completeness(4)'!$A$1:$A$55,1,FALSE) -> 04.5.510
A49: 01.1.218 | B49: Poultry other than chicken and turkey | C49: =VLOOKUP(A49,'Completeness(1)'!$A$1:$A$294,1,FALSE) -> 01.1.218 | E49: 04.5.520 | F49: Associated expenditures such as hire of meters, reading of meters, standing charges, etc | G49: =VLOOKUP(E49,'Completeness(4)'!$A$1:$A$55,1,FALSE) -> 04.5.520
A50: 01.1.219 | B50: Other meat (Frog's meat, turtle's meat, quail, etc.) | C50: =VLOOKUP(A50,'Completeness(1)'!$A$1:$A$294,1,FALSE) -> 01.1.219 | E50: 04.5.530 | F50: Ice used for cooling and refrigeration purposes | G50: =VLOOKUP(E50,'Completeness(4)'!$A$1:$A$55,1,FALSE) -> 04.5.530
A51: 01.1.220 | B51: Edible offal of bovine animals, fresh, chilled or frozen (swine, cattle, chicken, goats, horses, etc.) | C51: =VLOOKUP(A51,'Completeness(1)'!$A$1:$A$294,1,FALSE) -> 01.1.220
A52: 01.1.231 | B52: Dried and salted or smoked meat of bovine animals | C52: =VLOOKUP(A52,'Completeness(1)'!$A$1:$A$294,1,FALSE) -> 01.1.231
A53: 01.1.232 | B53: Dried and salted or smoked meat of chicken and other poultry meatbovine animals | C53: =VLOOKUP(A53,'Completeness(1)'!$A$1:$A$294,1,FALSE) -> 01.1.232
A54: 01.1.233 | B54: Dried and salted or smoked meat of edible offal | C54: =VLOOKUP(A54,'Completeness(1)'!$A$1:$A$294,1,FALSE) -> 01.1.233
A55: 01.1.239 | B55: Other dried, salted or smoked meat and edible offal, n.e.c. | C55: =VLOOKUP(A55,'Completeness(1)'!$A$1:$A$294,1,FALSE) -> 01.1.239
A56: 01.1.241 | B56: Tocino and tapa (beef, pork, chicken, etc.) | C56: =VLOOKUP(A56,'Completeness(1)'!$A$1:$A$294,1,FALSE) -> 01.1.241
A57: 01.1.242 | B57: Hotdog, longaniza, chorizo | C57: =VLOOKUP(A57,'Completeness(1)'!$A$1:$A$294,1,FALSE) -> 01.1.242
A58: 01.1.243 | B58: Corned beef | C58: =VLOOKUP(A58,'Completeness(1)'!$A$1:$A$294,1,FALSE) -> #N/A
A59: 01.1.244 | B59: Luncheon meat, meatloaf, embotido | C59: =VLOOKUP(A59,'Completeness(1)'!$A$1:$A$294,1,FALSE) -> 01.1.244
A60: 01.1.245 | B60: Sausages, bacon | C60: =VLOOKUP(A60,'Completeness(1)'!$A$1:$A$294,1,FALSE) -> 01.1.245
A61: 01.1.246 | B61: Salami, ham | C61: =VLOOKUP(A61,'Completeness(1)'!$A$1:$A$294,1,FALSE) -> 01.1.246
A62: 01.1.249 | B62: Other prepared or preserved meat and meat-based preparations, n.e.c. | C62: =VLOOKUP(A62,'Completeness(1)'!$A$1:$A$294,1,FALSE) -> 01.1.249
... A309: 01.2.250 | B309: Syrup and concentrates for the preparation of beverages | C309: =VLOOKUP(A309,'Completeness(1)'!$A$1:$A$294,1,FALSE) -> #N/A

Sheet Completeness(6)
A1: 06.1.111
A2: 06.1.112
A3: 06.1.113
A4: 06.1.114
A5: 06.1.115
A6: 06.1.122
A7: 06.1.129
A8: 06.1.191
A9: 06.1.200
A10: 06.1.310
A11: 06.1.320
A12: 06.1.330
... A25: 06.3.010
